// converted by version  [v3.0.4]
// on Wed Sep 16 14:25:46 SGT 2020

.package jcostest {
	.aid 0x55:0x55:0x55:0x55:0x55:0xFF;
	.version 1.0;

	.imports {
		0xA0:0x0:0x0:0x0:0x62:0x0:0x1 1.0;		//java/lang
		0xA0:0x0:0x0:0x0:0x62:0x1:0x2 1.5;		//javacard/security
		0xA0:0x0:0x0:0x0:0x62:0x1:0x1 1.5;		//javacard/framework
		0xA0:0x0:0x0:0x0:0x62:0x2:0x1 1.5;		//javacardx/crypto
	}

	.applet {
		0x55:0x55:0x55:0x55:0x55:0x1:0x0 JCOSTestApplet;
	}

	.constantPool {
		// 0
		instanceFieldRef 1.11 JCOSTestApplet/md;
		// 1
		instanceFieldRef 1.15 JCOSTestApplet/signer;
		// 2
		instanceFieldRef 3.1 JCOSTestApplet/cipher;
		// 3
		instanceFieldRef 1.22 JCOSTestApplet/ka;
		// 4
		instanceFieldRef 1.0 JCOSTestApplet/testKey1;
		// 5
		instanceFieldRef 1.0 JCOSTestApplet/testKey2;
		// 6
		instanceFieldRef 1.0 JCOSTestApplet/testKey3;
		// 7
		instanceFieldRef 1.0 JCOSTestApplet/testKey4;
		// 8
		instanceFieldRef 1.16 JCOSTestApplet/testKeyPair1;
		// 9
		instanceFieldRef 1.16 JCOSTestApplet/testKeyPair2;
		// 10
		instanceFieldRef byte JCOSTestApplet/testKey1Type;
		// 11
		instanceFieldRef byte JCOSTestApplet/testKey2Type;
		// 12
		instanceFieldRef byte JCOSTestApplet/testKey3Type;
		// 13
		instanceFieldRef byte JCOSTestApplet/testKey4Type;
		// 14
		instanceFieldRef byte JCOSTestApplet/testKey1PersistentType;
		// 15
		instanceFieldRef byte JCOSTestApplet/testKey2PersistentType;
		// 16
		instanceFieldRef byte JCOSTestApplet/testKey3PersistentType;
		// 17
		instanceFieldRef byte JCOSTestApplet/testKey4PersistentType;
		// 18
		instanceFieldRef byte[] JCOSTestApplet/arbitraryData;
		// 19
		instanceFieldRef byte[] JCOSTestApplet/b0;
		// 20
		instanceFieldRef byte[] JCOSTestApplet/b1;
		// 21
		staticFieldRef byte[] Constants/ansix9p521r1_r;
		// 22
		staticFieldRef byte[] Constants/SECP256K1_A;
		// 23
		staticFieldRef byte[] Constants/SECP256K1_B;
		// 24
		staticFieldRef byte[] Constants/SECP256K1_FIELD;
		// 25
		staticFieldRef byte[] Constants/SECP256K1_G;
		// 26
		staticFieldRef byte[] Constants/SECP256K1_R;
		// 27
		staticFieldRef byte[] Constants/brainpoolP256r1_a;
		// 28
		staticFieldRef byte[] Constants/brainpoolP256r1_b;
		// 29
		staticFieldRef byte[] Constants/brainpoolP256r1_field;
		// 30
		staticFieldRef byte[] Constants/brainpoolP256r1_g;
		// 31
		staticFieldRef byte[] Constants/brainpoolP256r1_r;
		// 32
		staticFieldRef byte[] Constants/brainpoolP384r1_a;
		// 33
		staticFieldRef byte[] Constants/brainpoolP384r1_b;
		// 34
		staticFieldRef byte[] Constants/brainpoolP384r1_field;
		// 35
		staticFieldRef byte[] Constants/brainpoolP384r1_g;
		// 36
		staticFieldRef byte[] Constants/brainpoolP384r1_r;
		// 37
		staticFieldRef byte[] Constants/brainpoolP512r1_a;
		// 38
		staticFieldRef byte[] Constants/brainpoolP512r1_b;
		// 39
		staticFieldRef byte[] Constants/brainpoolP512r1_field;
		// 40
		staticFieldRef byte[] Constants/brainpoolP512r1_g;
		// 41
		staticFieldRef byte[] Constants/brainpoolP512r1_r;
		// 42
		staticMethodRef 2.16.1([BS[BSS)S;		// javacard/framework/Util.arrayCopy([BS[BSS)S
		// 43
		.classRef JCOSTestApplet;
		// 44
		staticMethodRef JCOSTestApplet/<init>()V;
		// 45
		staticMethodRef 2.3.0()V;		// javacard/framework/Applet.<init>()V
		// 46
		staticMethodRef 0.0.0()V;		// java/lang/Object.<init>()V
		// 47
		.classRef 1.20;		// javacard/security/AESKey
		// 48
		.classRef 1.10;		// javacard/security/DESKey
		// 49
		.classRef 1.19;		// javacard/security/ECPublicKey
		// 50
		staticMethodRef AlternateKM/initECCurveParameters(Ljavacard/security/Key;B)V;
			.descriptor	Ljavacard/security/Key;	1.0;

		// 51
		.classRef 1.18;		// javacard/security/ECPrivateKey
		// 52
		.classRef 1.17;		// javacard/security/ECKey
		// 53
		staticFieldRef byte[] Constants/ansix9p256r1_a;
		// 54
		staticFieldRef byte[] Constants/ansix9p256r1_b;
		// 55
		staticFieldRef byte[] Constants/ansix9p256r1_field;
		// 56
		staticFieldRef byte[] Constants/ansix9p256r1_g;
		// 57
		staticFieldRef byte[] Constants/ansix9p256r1_r;
		// 58
		staticFieldRef byte[] Constants/ansix9p384r1_a;
		// 59
		staticFieldRef byte[] Constants/ansix9p384r1_b;
		// 60
		staticFieldRef byte[] Constants/ansix9p384r1_field;
		// 61
		staticFieldRef byte[] Constants/ansix9p384r1_g;
		// 62
		staticFieldRef byte[] Constants/ansix9p384r1_r;
		// 63
		staticFieldRef byte[] Constants/ansix9p521r1_a;
		// 64
		staticFieldRef byte[] Constants/ansix9p521r1_b;
		// 65
		staticMethodRef 2.8.13(SB)[B;		// javacard/framework/JCSystem.makeTransientByteArray(SB)[B
		// 66
		staticFieldRef byte[] Constants/ansix9p521r1_field;
		// 67
		staticFieldRef byte[] Constants/ansix9p521r1_g;
		// 68
		virtualMethodRef 2.3.1()V;		// register()V
		// 69
		virtualMethodRef 2.3.3()Z;		// selectingApplet()Z
		// 70
		virtualMethodRef 2.10.1()[B;		// getBuffer()[B
		// 71
		virtualMethodRef JCOSTestApplet/setKey(Ljavacard/framework/APDU;[B)V;
			.descriptor	Ljavacard/framework/APDU;	2.10;

		// 72
		virtualMethodRef JCOSTestApplet/setData(Ljavacard/framework/APDU;[B)V;
			.descriptor	Ljavacard/framework/APDU;	2.10;

		// 73
		virtualMethodRef JCOSTestApplet/getKey(Ljavacard/security/Key;B[BS)S;
			.descriptor	Ljavacard/security/Key;	1.0;

		// 74
		staticMethodRef 2.7.1(S)V;		// javacard/framework/ISOException.throwIt(S)V
		// 75
		virtualMethodRef 2.10.8(SS)V;		// setOutgoingAndSend(SS)V
		// 76
		virtualMethodRef JCOSTestApplet/encrypt(Ljavacard/framework/APDU;[B)V;
			.descriptor	Ljavacard/framework/APDU;	2.10;

		// 77
		virtualMethodRef JCOSTestApplet/decrypt(Ljavacard/framework/APDU;[B)V;
			.descriptor	Ljavacard/framework/APDU;	2.10;

		// 78
		virtualMethodRef JCOSTestApplet/derive(Ljavacard/framework/APDU;[B)V;
			.descriptor	Ljavacard/framework/APDU;	2.10;

		// 79
		virtualMethodRef JCOSTestApplet/doHash(Ljavacard/framework/APDU;[B)V;
			.descriptor	Ljavacard/framework/APDU;	2.10;

		// 80
		virtualMethodRef JCOSTestApplet/sign(Ljavacard/framework/APDU;[B)V;
			.descriptor	Ljavacard/framework/APDU;	2.10;

		// 81
		virtualMethodRef JCOSTestApplet/verify(Ljavacard/framework/APDU;[B)V;
			.descriptor	Ljavacard/framework/APDU;	2.10;

		// 82
		virtualMethodRef JCOSTestApplet/javaVMTests(Ljavacard/framework/APDU;[B)V;
			.descriptor	Ljavacard/framework/APDU;	2.10;

		// 83
		virtualMethodRef JCOSTestApplet/getKeyInstance(Ljavacard/security/Key;)V;
			.descriptor	Ljavacard/security/Key;	1.0;

		// 84
		virtualMethodRef JCOSTestApplet/getCipherInstance()V;
		// 85
		virtualMethodRef JCOSTestApplet/getSignerInstance()V;
		// 86
		virtualMethodRef JCOSTestApplet/getKeyAgreementInstance()V;
		// 87
		virtualMethodRef JCOSTestApplet/javaInstanceOfTest()B;
		// 88
		.classRef 1.0;		// javacard/security/Key
		// 89
		staticMethodRef 1.13.0(BSZ)Ljavacard/security/Key;;		// javacard/security/KeyBuilder.buildKey(BSZ)Ljavacard/security/Key;
			.descriptor	Ljavacard/security/Key;	1.0;

		// 90
		.classRef 1.8;		// javacard/security/RSAPrivateKey
		// 91
		.classRef 1.9;		// javacard/security/RSAPublicKey
		// 92
		staticMethodRef 2.16.5(BB)S;		// javacard/framework/Util.makeShort(BB)S
		// 93
		virtualMethodRef 3.1.2()B;		// getAlgorithm()B
		// 94
		virtualMethodRef 1.15.1()B;		// getAlgorithm()B
		// 95
		virtualMethodRef 1.22.2()B;		// getAlgorithm()B
		// 96
		virtualMethodRef 2.10.6()S;		// setIncomingAndReceive()S
		// 97
		virtualMethodRef 2.10.16()S;		// getOffsetCdata()S
		// 98
		staticMethodRef 2.16.3([BSSB)S;		// javacard/framework/Util.arrayFillNonAtomic([BSSB)S
		// 99
		virtualMethodRef JCOSTestApplet/buildPreciseKey(Ljavacard/security/Key;BS)Ljavacard/security/Key;;
			.descriptor	Ljavacard/security/Key;	1.0;
			.descriptor	Ljavacard/security/Key;	1.0;

		// 100
		virtualMethodRef JCOSTestApplet/setKey(Ljavacard/security/Key;BB[BSS)Z;
			.descriptor	Ljavacard/security/Key;	1.0;

		// 101
		staticMethodRef AlternateKM/setKey(Ljavacard/security/Key;B[BSS)Z;
			.descriptor	Ljavacard/security/Key;	1.0;

		// 102
		.classRef 1.12;		// javacard/security/CryptoException
		// 103
		staticMethodRef 3.1.0(BZ)Ljavacardx/crypto/Cipher;;		// javacardx/crypto/Cipher.getInstance(BZ)Ljavacardx/crypto/Cipher;
			.descriptor	Ljavacardx/crypto/Cipher;	3.1;

		// 104
		virtualMethodRef 3.1.3(Ljavacard/security/Key;B)V;		// init(Ljavacard/security/Key;B)V
			.descriptor	Ljavacard/security/Key;	1.0;

		// 105
		virtualMethodRef 3.1.4(Ljavacard/security/Key;B[BSS)V;		// init(Ljavacard/security/Key;B[BSS)V
			.descriptor	Ljavacard/security/Key;	1.0;

		// 106
		virtualMethodRef 3.1.5([BSS[BS)S;		// update([BSS[BS)S
		// 107
		virtualMethodRef 2.10.7()S;		// setOutgoing()S
		// 108
		virtualMethodRef 2.10.9(S)V;		// setOutgoingLength(S)V
		// 109
		virtualMethodRef 2.10.5([BSS)V;		// sendBytesLong([BSS)V
		// 110
		virtualMethodRef 1.12.1()S;		// getReason()S
		// 111
		virtualMethodRef 3.1.1([BSS[BS)S;		// doFinal([BSS[BS)S
		// 112
		staticMethodRef 1.22.0(BZ)Ljavacard/security/KeyAgreement;;		// javacard/security/KeyAgreement.getInstance(BZ)Ljavacard/security/KeyAgreement;
			.descriptor	Ljavacard/security/KeyAgreement;	1.22;

		// 113
		.classRef 1.2;		// javacard/security/PrivateKey
		// 114
		virtualMethodRef 1.22.1(Ljavacard/security/PrivateKey;)V;		// init(Ljavacard/security/PrivateKey;)V
			.descriptor	Ljavacard/security/PrivateKey;	1.2;

		// 115
		virtualMethodRef 1.22.3([BSS[BS)S;		// generateSecret([BSS[BS)S
		// 116
		staticMethodRef 1.15.0(BZ)Ljavacard/security/Signature;;		// javacard/security/Signature.getInstance(BZ)Ljavacard/security/Signature;
			.descriptor	Ljavacard/security/Signature;	1.15;

		// 117
		virtualMethodRef 1.15.3(Ljavacard/security/Key;B)V;		// init(Ljavacard/security/Key;B)V
			.descriptor	Ljavacard/security/Key;	1.0;

		// 118
		virtualMethodRef 1.15.4(Ljavacard/security/Key;B[BSS)V;		// init(Ljavacard/security/Key;B[BSS)V
			.descriptor	Ljavacard/security/Key;	1.0;

		// 119
		virtualMethodRef 1.15.6([BSS)V;		// update([BSS)V
		// 120
		virtualMethodRef 1.15.5([BSS[BS)S;		// sign([BSS[BS)S
		// 121
		virtualMethodRef 1.15.7([BSS[BSS)Z;		// verify([BSS[BSS)Z
		// 122
		staticMethodRef 2.16.2([BS[BSS)S;		// javacard/framework/Util.arrayCopyNonAtomic([BS[BSS)S
		// 123
		staticMethodRef AlternateKM/setData([BS[BSS)V;
		// 124
		staticMethodRef 2.16.6([BSS)S;		// javacard/framework/Util.setShort([BSS)S
		// 125
		staticMethodRef 1.11.0(BZ)Ljavacard/security/MessageDigest;;		// javacard/security/MessageDigest.getInstance(BZ)Ljavacard/security/MessageDigest;
			.descriptor	Ljavacard/security/MessageDigest;	1.11;

		// 126
		virtualMethodRef 1.11.2()B;		// getAlgorithm()B
		// 127
		virtualMethodRef 1.11.4()V;		// reset()V
		// 128
		virtualMethodRef 1.11.5([BSS)V;		// update([BSS)V
		// 129
		virtualMethodRef 1.11.1([BSS[BS)S;		// doFinal([BSS[BS)S
		// 130
		virtualMethodRef JCOSTestApplet/initECCurveParameters(Ljavacard/security/ECKey;B)Z;
			.descriptor	Ljavacard/security/ECKey;	1.17;

		// 131
		.classRef 0.2;		// java/lang/Exception
	}

	.class public AlternateKM 0 extends 0.0 {		// extends java/lang/Object

		.publicMethodTable 1 {
			equals(Ljava/lang/Object;)Z;
		}

		.packageMethodTable 0 {
		}

		.method public <init>()V 0 {
			.stack 1;
			.locals 0;

				L0:	aload_0;
					invokespecial 46;		// java/lang/Object.<init>()V
					return;
		}

		.method public static setKey(Ljavacard/security/Key;B[BSS)Z 1 {
			.stack 4;
			.locals 0;

			.descriptor	Ljavacard/security/Key;	1.0;

				L0:	aload_0;
					instanceof 0 47;		// T_CLASSORINTERFACE javacard/security/AESKey
					ifeq L2;
				L1:	aload_0;
					checkcast 0 47;		// T_CLASSORINTERFACE javacard/security/AESKey
					aload_2;
					sload_3;
					invokeinterface 3 47 4;		// javacard/security/AESKey
					goto L9;
				L2:	aload_0;
					instanceof 0 48;		// T_CLASSORINTERFACE javacard/security/DESKey
					ifeq L4;
				L3:	aload_0;
					checkcast 0 48;		// T_CLASSORINTERFACE javacard/security/DESKey
					aload_2;
					sload_3;
					invokeinterface 3 48 5;		// javacard/security/DESKey
					goto L9;
				L4:	aload_0;
					instanceof 0 49;		// T_CLASSORINTERFACE javacard/security/ECPublicKey
					ifeq L6;
				L5:	aload_0;
					sload_1;
					invokestatic 50;		// jcostest/AlternateKM.initECCurveParameters(Ljavacard/security/Key;B)V
					aload_0;
					checkcast 0 49;		// T_CLASSORINTERFACE javacard/security/ECPublicKey
					aload_2;
					sload_3;
					sload 4;
					invokeinterface 4 49 18;		// javacard/security/ECPublicKey
					goto L9;
				L6:	aload_0;
					instanceof 0 51;		// T_CLASSORINTERFACE javacard/security/ECPrivateKey
					ifeq L8;
				L7:	aload_0;
					sload_1;
					invokestatic 50;		// jcostest/AlternateKM.initECCurveParameters(Ljavacard/security/Key;B)V
					aload_0;
					checkcast 0 51;		// T_CLASSORINTERFACE javacard/security/ECPrivateKey
					aload_2;
					sload_3;
					sload 4;
					invokeinterface 4 51 18;		// javacard/security/ECPrivateKey
					goto L9;
				L8:	sconst_0;
					sreturn;
				L9:	sconst_1;
					sreturn;
		}

		.method public static initECCurveParameters(Ljavacard/security/Key;B)V 2 {
			.stack 4;
			.locals 0;

			.descriptor	Ljavacard/security/Key;	1.0;

				L0:	sload_1;
					sconst_1;
					if_scmpne L2;
				L1:	aload_0;
					checkcast 0 52;		// T_CLASSORINTERFACE javacard/security/ECKey
					getstatic_a 53;		// reference jcostest/Constants.ansix9p256r1_a
					sconst_0;
					getstatic_a 53;		// reference jcostest/Constants.ansix9p256r1_a
					arraylength;
					invokeinterface 4 52 3;		// javacard/security/ECKey
					aload_0;
					checkcast 0 52;		// T_CLASSORINTERFACE javacard/security/ECKey
					getstatic_a 54;		// reference jcostest/Constants.ansix9p256r1_b
					sconst_0;
					getstatic_a 54;		// reference jcostest/Constants.ansix9p256r1_b
					arraylength;
					invokeinterface 4 52 4;		// javacard/security/ECKey
					aload_0;
					checkcast 0 52;		// T_CLASSORINTERFACE javacard/security/ECKey
					getstatic_a 55;		// reference jcostest/Constants.ansix9p256r1_field
					sconst_0;
					getstatic_a 55;		// reference jcostest/Constants.ansix9p256r1_field
					arraylength;
					invokeinterface 4 52 0;		// javacard/security/ECKey
					aload_0;
					checkcast 0 52;		// T_CLASSORINTERFACE javacard/security/ECKey
					getstatic_a 56;		// reference jcostest/Constants.ansix9p256r1_g
					sconst_0;
					getstatic_a 56;		// reference jcostest/Constants.ansix9p256r1_g
					arraylength;
					invokeinterface 4 52 5;		// javacard/security/ECKey
					aload_0;
					checkcast 0 52;		// T_CLASSORINTERFACE javacard/security/ECKey
					getstatic_a 57;		// reference jcostest/Constants.ansix9p256r1_r
					sconst_0;
					getstatic_a 57;		// reference jcostest/Constants.ansix9p256r1_r
					arraylength;
					invokeinterface 4 52 6;		// javacard/security/ECKey
					aload_0;
					checkcast 0 52;		// T_CLASSORINTERFACE javacard/security/ECKey
					sconst_1;
					invokeinterface 2 52 7;		// javacard/security/ECKey
					goto_w L14;
				L2:	sload_1;
					sconst_2;
					if_scmpne L4;
				L3:	aload_0;
					checkcast 0 52;		// T_CLASSORINTERFACE javacard/security/ECKey
					getstatic_a 58;		// reference jcostest/Constants.ansix9p384r1_a
					sconst_0;
					getstatic_a 58;		// reference jcostest/Constants.ansix9p384r1_a
					arraylength;
					invokeinterface 4 52 3;		// javacard/security/ECKey
					aload_0;
					checkcast 0 52;		// T_CLASSORINTERFACE javacard/security/ECKey
					getstatic_a 59;		// reference jcostest/Constants.ansix9p384r1_b
					sconst_0;
					getstatic_a 59;		// reference jcostest/Constants.ansix9p384r1_b
					arraylength;
					invokeinterface 4 52 4;		// javacard/security/ECKey
					aload_0;
					checkcast 0 52;		// T_CLASSORINTERFACE javacard/security/ECKey
					getstatic_a 60;		// reference jcostest/Constants.ansix9p384r1_field
					sconst_0;
					getstatic_a 60;		// reference jcostest/Constants.ansix9p384r1_field
					arraylength;
					invokeinterface 4 52 0;		// javacard/security/ECKey
					aload_0;
					checkcast 0 52;		// T_CLASSORINTERFACE javacard/security/ECKey
					getstatic_a 61;		// reference jcostest/Constants.ansix9p384r1_g
					sconst_0;
					getstatic_a 61;		// reference jcostest/Constants.ansix9p384r1_g
					arraylength;
					invokeinterface 4 52 5;		// javacard/security/ECKey
					aload_0;
					checkcast 0 52;		// T_CLASSORINTERFACE javacard/security/ECKey
					getstatic_a 62;		// reference jcostest/Constants.ansix9p384r1_r
					sconst_0;
					getstatic_a 62;		// reference jcostest/Constants.ansix9p384r1_r
					arraylength;
					invokeinterface 4 52 6;		// javacard/security/ECKey
					aload_0;
					checkcast 0 52;		// T_CLASSORINTERFACE javacard/security/ECKey
					sconst_1;
					invokeinterface 2 52 7;		// javacard/security/ECKey
					goto_w L14;
				L4:	sload_1;
					sconst_3;
					if_scmpne L6;
				L5:	aload_0;
					checkcast 0 52;		// T_CLASSORINTERFACE javacard/security/ECKey
					getstatic_a 63;		// reference jcostest/Constants.ansix9p521r1_a
					sconst_0;
					getstatic_a 63;		// reference jcostest/Constants.ansix9p521r1_a
					arraylength;
					invokeinterface 4 52 3;		// javacard/security/ECKey
					aload_0;
					checkcast 0 52;		// T_CLASSORINTERFACE javacard/security/ECKey
					getstatic_a 64;		// reference jcostest/Constants.ansix9p521r1_b
					sconst_0;
					getstatic_a 64;		// reference jcostest/Constants.ansix9p521r1_b
					arraylength;
					invokeinterface 4 52 4;		// javacard/security/ECKey
					aload_0;
					checkcast 0 52;		// T_CLASSORINTERFACE javacard/security/ECKey
					getstatic_a 66;		// reference jcostest/Constants.ansix9p521r1_field
					sconst_0;
					getstatic_a 66;		// reference jcostest/Constants.ansix9p521r1_field
					arraylength;
					invokeinterface 4 52 0;		// javacard/security/ECKey
					aload_0;
					checkcast 0 52;		// T_CLASSORINTERFACE javacard/security/ECKey
					getstatic_a 67;		// reference jcostest/Constants.ansix9p521r1_g
					sconst_0;
					getstatic_a 67;		// reference jcostest/Constants.ansix9p521r1_g
					arraylength;
					invokeinterface 4 52 5;		// javacard/security/ECKey
					aload_0;
					checkcast 0 52;		// T_CLASSORINTERFACE javacard/security/ECKey
					getstatic_a 21;		// reference jcostest/Constants.ansix9p521r1_r
					sconst_0;
					getstatic_a 21;		// reference jcostest/Constants.ansix9p521r1_r
					arraylength;
					invokeinterface 4 52 6;		// javacard/security/ECKey
					aload_0;
					checkcast 0 52;		// T_CLASSORINTERFACE javacard/security/ECKey
					sconst_1;
					invokeinterface 2 52 7;		// javacard/security/ECKey
					goto_w L14;
				L6:	sload_1;
					sconst_4;
					if_scmpne L8;
				L7:	aload_0;
					checkcast 0 52;		// T_CLASSORINTERFACE javacard/security/ECKey
					getstatic_a 22;		// reference jcostest/Constants.SECP256K1_A
					sconst_0;
					getstatic_a 22;		// reference jcostest/Constants.SECP256K1_A
					arraylength;
					invokeinterface 4 52 3;		// javacard/security/ECKey
					aload_0;
					checkcast 0 52;		// T_CLASSORINTERFACE javacard/security/ECKey
					getstatic_a 23;		// reference jcostest/Constants.SECP256K1_B
					sconst_0;
					getstatic_a 23;		// reference jcostest/Constants.SECP256K1_B
					arraylength;
					invokeinterface 4 52 4;		// javacard/security/ECKey
					aload_0;
					checkcast 0 52;		// T_CLASSORINTERFACE javacard/security/ECKey
					getstatic_a 24;		// reference jcostest/Constants.SECP256K1_FIELD
					sconst_0;
					getstatic_a 24;		// reference jcostest/Constants.SECP256K1_FIELD
					arraylength;
					invokeinterface 4 52 0;		// javacard/security/ECKey
					aload_0;
					checkcast 0 52;		// T_CLASSORINTERFACE javacard/security/ECKey
					getstatic_a 25;		// reference jcostest/Constants.SECP256K1_G
					sconst_0;
					getstatic_a 25;		// reference jcostest/Constants.SECP256K1_G
					arraylength;
					invokeinterface 4 52 5;		// javacard/security/ECKey
					aload_0;
					checkcast 0 52;		// T_CLASSORINTERFACE javacard/security/ECKey
					getstatic_a 26;		// reference jcostest/Constants.SECP256K1_R
					sconst_0;
					getstatic_a 26;		// reference jcostest/Constants.SECP256K1_R
					arraylength;
					invokeinterface 4 52 6;		// javacard/security/ECKey
					aload_0;
					checkcast 0 52;		// T_CLASSORINTERFACE javacard/security/ECKey
					sconst_1;
					invokeinterface 2 52 7;		// javacard/security/ECKey
					goto_w L14;
				L8:	sload_1;
					sconst_5;
					if_scmpne L10;
				L9:	aload_0;
					checkcast 0 52;		// T_CLASSORINTERFACE javacard/security/ECKey
					getstatic_a 27;		// reference jcostest/Constants.brainpoolP256r1_a
					sconst_0;
					getstatic_a 27;		// reference jcostest/Constants.brainpoolP256r1_a
					arraylength;
					invokeinterface 4 52 3;		// javacard/security/ECKey
					aload_0;
					checkcast 0 52;		// T_CLASSORINTERFACE javacard/security/ECKey
					getstatic_a 28;		// reference jcostest/Constants.brainpoolP256r1_b
					sconst_0;
					getstatic_a 28;		// reference jcostest/Constants.brainpoolP256r1_b
					arraylength;
					invokeinterface 4 52 4;		// javacard/security/ECKey
					aload_0;
					checkcast 0 52;		// T_CLASSORINTERFACE javacard/security/ECKey
					getstatic_a 29;		// reference jcostest/Constants.brainpoolP256r1_field
					sconst_0;
					getstatic_a 29;		// reference jcostest/Constants.brainpoolP256r1_field
					arraylength;
					invokeinterface 4 52 0;		// javacard/security/ECKey
					aload_0;
					checkcast 0 52;		// T_CLASSORINTERFACE javacard/security/ECKey
					getstatic_a 30;		// reference jcostest/Constants.brainpoolP256r1_g
					sconst_0;
					getstatic_a 30;		// reference jcostest/Constants.brainpoolP256r1_g
					arraylength;
					invokeinterface 4 52 5;		// javacard/security/ECKey
					aload_0;
					checkcast 0 52;		// T_CLASSORINTERFACE javacard/security/ECKey
					getstatic_a 31;		// reference jcostest/Constants.brainpoolP256r1_r
					sconst_0;
					getstatic_a 31;		// reference jcostest/Constants.brainpoolP256r1_r
					arraylength;
					invokeinterface 4 52 6;		// javacard/security/ECKey
					aload_0;
					checkcast 0 52;		// T_CLASSORINTERFACE javacard/security/ECKey
					sconst_1;
					invokeinterface 2 52 7;		// javacard/security/ECKey
					goto_w L14;
				L10:	sload_1;
					bspush 6;
					if_scmpne L12;
				L11:	aload_0;
					checkcast 0 52;		// T_CLASSORINTERFACE javacard/security/ECKey
					getstatic_a 32;		// reference jcostest/Constants.brainpoolP384r1_a
					sconst_0;
					getstatic_a 32;		// reference jcostest/Constants.brainpoolP384r1_a
					arraylength;
					invokeinterface 4 52 3;		// javacard/security/ECKey
					aload_0;
					checkcast 0 52;		// T_CLASSORINTERFACE javacard/security/ECKey
					getstatic_a 33;		// reference jcostest/Constants.brainpoolP384r1_b
					sconst_0;
					getstatic_a 33;		// reference jcostest/Constants.brainpoolP384r1_b
					arraylength;
					invokeinterface 4 52 4;		// javacard/security/ECKey
					aload_0;
					checkcast 0 52;		// T_CLASSORINTERFACE javacard/security/ECKey
					getstatic_a 34;		// reference jcostest/Constants.brainpoolP384r1_field
					sconst_0;
					getstatic_a 34;		// reference jcostest/Constants.brainpoolP384r1_field
					arraylength;
					invokeinterface 4 52 0;		// javacard/security/ECKey
					aload_0;
					checkcast 0 52;		// T_CLASSORINTERFACE javacard/security/ECKey
					getstatic_a 35;		// reference jcostest/Constants.brainpoolP384r1_g
					sconst_0;
					getstatic_a 35;		// reference jcostest/Constants.brainpoolP384r1_g
					arraylength;
					invokeinterface 4 52 5;		// javacard/security/ECKey
					aload_0;
					checkcast 0 52;		// T_CLASSORINTERFACE javacard/security/ECKey
					getstatic_a 36;		// reference jcostest/Constants.brainpoolP384r1_r
					sconst_0;
					getstatic_a 36;		// reference jcostest/Constants.brainpoolP384r1_r
					arraylength;
					invokeinterface 4 52 6;		// javacard/security/ECKey
					aload_0;
					checkcast 0 52;		// T_CLASSORINTERFACE javacard/security/ECKey
					sconst_1;
					invokeinterface 2 52 7;		// javacard/security/ECKey
					goto L14;
				L12:	sload_1;
					bspush 7;
					if_scmpne L14;
				L13:	aload_0;
					checkcast 0 52;		// T_CLASSORINTERFACE javacard/security/ECKey
					getstatic_a 37;		// reference jcostest/Constants.brainpoolP512r1_a
					sconst_0;
					getstatic_a 37;		// reference jcostest/Constants.brainpoolP512r1_a
					arraylength;
					invokeinterface 4 52 3;		// javacard/security/ECKey
					aload_0;
					checkcast 0 52;		// T_CLASSORINTERFACE javacard/security/ECKey
					getstatic_a 38;		// reference jcostest/Constants.brainpoolP512r1_b
					sconst_0;
					getstatic_a 38;		// reference jcostest/Constants.brainpoolP512r1_b
					arraylength;
					invokeinterface 4 52 4;		// javacard/security/ECKey
					aload_0;
					checkcast 0 52;		// T_CLASSORINTERFACE javacard/security/ECKey
					getstatic_a 39;		// reference jcostest/Constants.brainpoolP512r1_field
					sconst_0;
					getstatic_a 39;		// reference jcostest/Constants.brainpoolP512r1_field
					arraylength;
					invokeinterface 4 52 0;		// javacard/security/ECKey
					aload_0;
					checkcast 0 52;		// T_CLASSORINTERFACE javacard/security/ECKey
					getstatic_a 40;		// reference jcostest/Constants.brainpoolP512r1_g
					sconst_0;
					getstatic_a 40;		// reference jcostest/Constants.brainpoolP512r1_g
					arraylength;
					invokeinterface 4 52 5;		// javacard/security/ECKey
					aload_0;
					checkcast 0 52;		// T_CLASSORINTERFACE javacard/security/ECKey
					getstatic_a 41;		// reference jcostest/Constants.brainpoolP512r1_r
					sconst_0;
					getstatic_a 41;		// reference jcostest/Constants.brainpoolP512r1_r
					arraylength;
					invokeinterface 4 52 6;		// javacard/security/ECKey
					aload_0;
					checkcast 0 52;		// T_CLASSORINTERFACE javacard/security/ECKey
					sconst_1;
					invokeinterface 2 52 7;		// javacard/security/ECKey
				L14:	return;
		}

		.method public static setData([BS[BSS)V 3 {
			.stack 5;
			.locals 0;

				L0:	aload_0;
					sload_1;
					aload_2;
					sload_3;
					sload 4;
					invokestatic 42;		// javacard/framework/Util.arrayCopy([BS[BSS)S
					pop;
					return;
		}

	}

	.class public Constants 1 extends 0.0 {		// extends java/lang/Object

		.fields {
			protected static byte[] ansix9p256r1_field 0 = {-1,-1,-1,-1,0,0,0,1,0,0,0,0,0,0,0,0,0,0,0,0,-1,-1,-1,-1,-1,-1,-1,-1,-1,-1,-1,-1};		// [B
			protected static byte[] ansix9p256r1_a 1 = {-1,-1,-1,-1,0,0,0,1,0,0,0,0,0,0,0,0,0,0,0,0,-1,-1,-1,-1,-1,-1,-1,-1,-1,-1,-1,-4};		// [B
			protected static byte[] ansix9p256r1_b 2 = {90,-58,53,-40,-86,58,-109,-25,-77,-21,-67,85,118,-104,-122,-68,101,29,6,-80,-52,83,-80,-10,59,-50,60,62,39,-46,96,75};		// [B
			protected static byte[] ansix9p256r1_g 3 = {4,107,23,-47,-14,-31,44,66,71,-8,-68,-26,-27,99,-92,64,-14,119,3,125,-127,45,-21,51,-96,-12,-95,57,69,-40,-104,-62,-106,79,-29,66,-30,-2,26,127,-101,-114,-25,-21,74,124,15,-98,22,43,-50,51,87,107,49,94,-50,-53,-74,64,104,55,-65,81,-11};		// [B
			protected static byte[] ansix9p256r1_r 4 = {-1,-1,-1,-1,0,0,0,0,-1,-1,-1,-1,-1,-1,-1,-1,-68,-26,-6,-83,-89,23,-98,-124,-13,-71,-54,-62,-4,99,37,81};		// [B
			protected static byte[] ansix9p384r1_field 5 = {-1,-1,-1,-1,-1,-1,-1,-1,-1,-1,-1,-1,-1,-1,-1,-1,-1,-1,-1,-1,-1,-1,-1,-1,-1,-1,-1,-1,-1,-1,-1,-2,-1,-1,-1,-1,0,0,0,0,0,0,0,0,-1,-1,-1,-1};		// [B
			protected static byte[] ansix9p384r1_a 6 = {-1,-1,-1,-1,-1,-1,-1,-1,-1,-1,-1,-1,-1,-1,-1,-1,-1,-1,-1,-1,-1,-1,-1,-1,-1,-1,-1,-1,-1,-1,-1,-2,-1,-1,-1,-1,0,0,0,0,0,0,0,0,-1,-1,-1,-4};		// [B
			protected static byte[] ansix9p384r1_b 7 = {-77,49,47,-89,-30,62,-25,-28,-104,-114,5,107,-29,-8,45,25,24,29,-100,110,-2,-127,65,18,3,20,8,-113,80,19,-121,90,-58,86,57,-115,-118,46,-47,-99,42,-123,-56,-19,-45,-20,42,-17};		// [B
			protected static byte[] ansix9p384r1_g 8 = {4,-86,-121,-54,34,-66,-117,5,55,-114,-79,-57,30,-13,32,-83,116,110,29,59,98,-117,-89,-101,-104,89,-9,65,-32,-126,84,42,56,85,2,-14,93,-65,85,41,108,58,84,94,56,114,118,10,-73,54,23,-34,74,-106,38,44,111,93,-98,-104,-65,-110,-110,-36,41,-8,-12,29,-67,40,-102,20,124,-23,-38,49,19,-75,-16,-72,-64,10,96,-79,-50,29,126,-127,-99,122,67,29,124,-112,-22,14,95};		// [B
			protected static byte[] ansix9p384r1_r 9 = {-1,-1,-1,-1,-1,-1,-1,-1,-1,-1,-1,-1,-1,-1,-1,-1,-1,-1,-1,-1,-1,-1,-1,-1,-57,99,77,-127,-12,55,45,-33,88,26,13,-78,72,-80,-89,122,-20,-20,25,106,-52,-59,41,115};		// [B
			protected static byte[] ansix9p521r1_field 10 = {1,-1,-1,-1,-1,-1,-1,-1,-1,-1,-1,-1,-1,-1,-1,-1,-1,-1,-1,-1,-1,-1,-1,-1,-1,-1,-1,-1,-1,-1,-1,-1,-1,-1,-1,-1,-1,-1,-1,-1,-1,-1,-1,-1,-1,-1,-1,-1,-1,-1,-1,-1,-1,-1,-1,-1,-1,-1,-1,-1,-1,-1,-1,-1,-1,-1};		// [B
			protected static byte[] ansix9p521r1_a 11 = {1,-1,-1,-1,-1,-1,-1,-1,-1,-1,-1,-1,-1,-1,-1,-1,-1,-1,-1,-1,-1,-1,-1,-1,-1,-1,-1,-1,-1,-1,-1,-1,-1,-1,-1,-1,-1,-1,-1,-1,-1,-1,-1,-1,-1,-1,-1,-1,-1,-1,-1,-1,-1,-1,-1,-1,-1,-1,-1,-1,-1,-1,-1,-1,-1,-4};		// [B
			protected static byte[] ansix9p521r1_b 12 = {0,81,-107,62,-71,97,-114,28,-102,31,-110,-102,33,-96,-74,-123,64,-18,-94,-38,114,91,-103,-77,21,-13,-72,-76,-119,-111,-114,-15,9,-31,86,25,57,81,-20,126,-109,123,22,82,-64,-67,59,-79,-65,7,53,115,-33,-120,61,44,52,-15,-17,69,31,-44,107,80,63,0};		// [B
			protected static byte[] ansix9p521r1_g 13 = {4,0,-58,-123,-114,6,-73,4,4,-23,-51,-98,62,-53,102,35,-107,-76,66,-100,100,-127,57,5,63,-75,33,-8,40,-81,96,107,77,61,-70,-95,75,94,119,-17,-25,89,40,-2,29,-63,39,-94,-1,-88,-34,51,72,-77,-63,-123,106,66,-101,-7,126,126,49,-62,-27,-67,102,1,24,57,41,106,120,-102,59,-64,4,92,-118,95,-76,44,125,27,-39,-104,-11,68,73,87,-101,68,104,23,-81,-67,23,39,62,102,44,-105,-18,114,-103,94,-12,38,64,-59,80,-71,1,63,-83,7,97,53,60,112,-122,-94,114,-62,64,-120,-66,-108,118,-97,-47,102,80};		// [B
			protected static byte[] ansix9p521r1_r 14 = {1,-1,-1,-1,-1,-1,-1,-1,-1,-1,-1,-1,-1,-1,-1,-1,-1,-1,-1,-1,-1,-1,-1,-1,-1,-1,-1,-1,-1,-1,-1,-1,-1,-6,81,-122,-121,-125,-65,47,-106,107,127,-52,1,72,-9,9,-91,-48,59,-75,-55,-72,-119,-100,71,-82,-69,111,-73,30,-111,56,100,9};		// [B
			protected static byte[] brainpoolP256r1_field 15 = {-87,-5,87,-37,-95,-18,-87,-68,62,102,10,-112,-99,-125,-115,114,110,59,-10,35,-43,38,32,40,32,19,72,29,31,110,83,119};		// [B
			protected static byte[] brainpoolP256r1_a 16 = {125,90,9,117,-4,44,48,87,-18,-10,117,48,65,122,-1,-25,-5,-128,85,-63,38,-36,92,108,-23,74,75,68,-13,48,-75,-39};		// [B
			protected static byte[] brainpoolP256r1_b 17 = {38,-36,92,108,-23,74,75,68,-13,48,-75,-39,-69,-41,124,-65,-107,-124,22,41,92,-9,-31,-50,107,-52,-36,24,-1,-116,7,-74};		// [B
			protected static byte[] brainpoolP256r1_g 18 = {4,-117,-46,-82,-71,-53,126,87,-53,44,75,72,47,-4,-127,-73,-81,-71,-34,39,-31,-29,-67,35,-62,58,68,83,-67,-102,-50,50,98,84,126,-8,53,-61,-38,-60,-3,-105,-8,70,26,20,97,29,-55,-62,119,69,19,45,-19,-114,84,92,29,84,-57,47,4,105,-105};		// [B
			protected static byte[] brainpoolP256r1_r 19 = {-87,-5,87,-37,-95,-18,-87,-68,62,102,10,-112,-99,-125,-115,113,-116,57,122,-93,-75,97,-90,-9,-112,30,14,-126,-105,72,86,-89};		// [B
			protected static byte[] brainpoolP384r1_field 20 = {-116,-71,30,-126,-93,56,109,40,15,93,111,126,80,-26,65,-33,21,47,113,9,-19,84,86,-76,18,-79,-38,25,127,-73,17,35,-84,-45,-89,41,-112,29,26,113,-121,71,0,19,49,7,-20,83};		// [B
			protected static byte[] brainpoolP384r1_a 21 = {123,-61,-126,-58,61,-116,21,12,60,114,8,10,-50,5,-81,-96,-62,-66,-94,-114,79,-78,39,-121,19,-111,101,-17,-70,-111,-7,15,-118,-91,-127,74,80,58,-44,-21,4,-88,-57,-35,34,-50,40,38};		// [B
			protected static byte[] brainpoolP384r1_b 22 = {4,-88,-57,-35,34,-50,40,38,-117,57,-75,84,22,-16,68,124,47,-73,125,-31,7,-36,-46,-90,46,-120,14,-91,62,-21,98,-43,124,-76,57,2,-107,-37,-55,-108,58,-73,-122,-106,-6,80,76,17};		// [B
			protected static byte[] brainpoolP384r1_g 23 = {4,29,28,100,-16,104,-49,69,-1,-94,-90,58,-127,-73,-63,63,107,-120,71,-93,-25,126,-15,79,-29,-37,127,-54,-2,12,-67,16,-24,-24,38,-32,52,54,-42,70,-86,-17,-121,-78,-30,71,-44,-81,30,-118,-66,29,117,32,-7,-62,-92,92,-79,-21,-114,-107,-49,-43,82,98,-73,11,41,-2,-20,88,100,-31,-100,5,79,-7,-111,41,40,14,70,70,33,119,-111,-127,17,66,-126,3,65,38,60,83,21};		// [B
			protected static byte[] brainpoolP384r1_r 24 = {-116,-71,30,-126,-93,56,109,40,15,93,111,126,80,-26,65,-33,21,47,113,9,-19,84,86,-77,31,22,110,108,-84,4,37,-89,-49,58,-74,-81,107,127,-61,16,59,-120,50,2,-23,4,101,101};		// [B
			protected static byte[] brainpoolP512r1_field 25 = {-86,-35,-99,-72,-37,-23,-60,-117,63,-44,-26,-82,51,-55,-4,7,-53,48,-115,-77,-77,-55,-46,14,-42,99,-100,-54,112,51,8,113,125,77,-101,0,-101,-58,104,66,-82,-51,-95,42,-26,-93,-128,-26,40,-127,-1,47,45,-126,-58,-123,40,-86,96,86,88,58,72,-13};		// [B
			protected static byte[] brainpoolP512r1_a 26 = {120,48,-93,49,-117,96,59,-119,-30,50,113,69,-84,35,76,-59,-108,-53,-35,-115,61,-7,22,16,-88,52,65,-54,-22,-104,99,-68,45,-19,93,90,-88,37,58,-95,10,46,-15,-55,-117,-102,-56,-75,127,17,23,-89,43,-14,-57,-71,-25,-63,-84,77,119,-4,-108,-54};		// [B
			protected static byte[] brainpoolP512r1_b 27 = {61,-7,22,16,-88,52,65,-54,-22,-104,99,-68,45,-19,93,90,-88,37,58,-95,10,46,-15,-55,-117,-102,-56,-75,127,17,23,-89,43,-14,-57,-71,-25,-63,-84,77,119,-4,-108,-54,-36,8,62,103,-104,64,80,-73,94,-70,-27,-35,40,9,-67,99,-128,22,-9,35};		// [B
			protected static byte[] brainpoolP512r1_g 28 = {4,-127,-82,-28,-67,-40,46,-39,100,90,33,50,46,-100,76,106,-109,-123,-19,-97,112,-75,-39,22,-63,-76,59,98,-18,-12,-48,9,-114,-1,59,31,120,-30,-48,-44,-115,80,-47,104,123,-109,-71,125,95,124,109,80,71,64,106,94,104,-117,53,34,9,-68,-71,-8,34,125,-34,56,93,86,99,50,-20,-64,-22,-65,-87,-49,120,34,-3,-14,9,-9,0,36,-91,123,26,-96,0,-59,91,-120,31,-127,17,-78,-36,-34,73,74,95,72,94,91,-54,75,-40,-118,39,99,-82,-47,-54,43,47,-88,-16,84,6,120,-51,30,15,58,-40,8,-110};		// [B
			protected static byte[] brainpoolP512r1_r 29 = {-86,-35,-99,-72,-37,-23,-60,-117,63,-44,-26,-82,51,-55,-4,7,-53,48,-115,-77,-77,-55,-46,14,-42,99,-100,-54,112,51,8,112,85,62,92,65,76,-87,38,25,65,-122,97,25,127,-84,16,71,29,-79,-45,-127,8,93,-38,-35,-75,-121,-106,-126,-100,-87,0,105};		// [B
			protected static final byte[] SECP256K1_FIELD 30 = {-1,-1,-1,-1,-1,-1,-1,-1,-1,-1,-1,-1,-1,-1,-1,-1,-1,-1,-1,-1,-1,-1,-1,-1,-1,-1,-1,-2,-1,-1,-4,47};		// [B
			protected static final byte[] SECP256K1_A 31 = {0,0,0,0,0,0,0,0,0,0,0,0,0,0,0,0,0,0,0,0,0,0,0,0,0,0,0,0,0,0,0,0};		// [B
			protected static final byte[] SECP256K1_B 32 = {0,0,0,0,0,0,0,0,0,0,0,0,0,0,0,0,0,0,0,0,0,0,0,0,0,0,0,0,0,0,0,7};		// [B
			protected static final byte[] SECP256K1_G 33 = {4,121,-66,102,126,-7,-36,-69,-84,85,-96,98,-107,-50,-121,11,7,2,-101,-4,-37,45,-50,40,-39,89,-14,-127,91,22,-8,23,-104,72,58,-38,119,38,-93,-60,101,93,-92,-5,-4,14,17,8,-88,-3,23,-76,72,-90,-123,84,25,-100,71,-48,-113,-5,16,-44,-72};		// [B
			static final byte[] SECP256K1_R = {-1,-1,-1,-1,-1,-1,-1,-1,-1,-1,-1,-1,-1,-1,-1,-2,-70,-82,-36,-26,-81,72,-96,59,-65,-46,94,-116,-48,54,65,65};		// [B
		}

		.publicMethodTable 1 {
			equals(Ljava/lang/Object;)Z;
		}

		.packageMethodTable 0 {
		}

		.method public <init>()V 0 {
			.stack 1;
			.locals 0;

				L0:	aload_0;
					invokespecial 46;		// java/lang/Object.<init>()V
					return;
		}

	}

	.class public JCOSTestApplet 2 extends 2.3 {		// extends javacard/framework/Applet

		.fields {
			public byte[] arbitraryData 0;		// [B
			private 1.11 md 1;		// Ljavacard/security/MessageDigest;
			private 1.15 signer 2;		// Ljavacard/security/Signature;
			private 3.1 cipher 3;		// Ljavacardx/crypto/Cipher;
			private 1.22 ka 4;		// Ljavacard/security/KeyAgreement;
			private 1.0 testKey1 5;		// Ljavacard/security/Key;
			private 1.0 testKey2 6;		// Ljavacard/security/Key;
			private 1.0 testKey3 7;		// Ljavacard/security/Key;
			private 1.0 testKey4 8;		// Ljavacard/security/Key;
			private 1.16 testKeyPair1 9;		// Ljavacard/security/KeyPair;
			private 1.16 testKeyPair2 10;		// Ljavacard/security/KeyPair;
			private byte[] b0 11;		// [B
			private byte[] b1 12;		// [B
			private byte testKey1Type 13;		// B
			private byte testKey2Type 14;		// B
			private byte testKey3Type 15;		// B
			private byte testKey4Type 16;		// B
			private byte testKey1PersistentType 17;		// B
			private byte testKey2PersistentType 18;		// B
			private byte testKey3PersistentType 19;		// B
			private byte testKey4PersistentType 20;		// B
			public static final byte INS_SET_KEY = 1;		// B
			public static final byte INS_SET_DATA = 2;		// B
			public static final byte INS_GET_KEY = 3;		// B
			public static final byte INS_GET_DATA = 4;		// B
			public static final byte INS_ENCRYPT = 5;		// B
			public static final byte INS_DECRYPT = 6;		// B
			public static final byte INS_DERIVE = 7;		// B
			public static final byte INS_HASH = 8;		// B
			public static final byte INS_SIGN = 9;		// B
			public static final byte INS_VERIFY = 10;		// B
			public static final byte INS_JAVA = 11;		// B
			public static final byte P1_SET = 1;		// B
			public static final byte P1_GET = 2;		// B
			public static final byte P1_IS_SET = 3;		// B
			public static final byte P1_RESET = 4;		// B
			public static final byte P1_UPDATE = 5;		// B
			public static final byte P1_FINAL = 6;		// B
			public static final byte P1_LOAD_FROM_MAIN = 7;		// B
			public static final byte P1_LOAD_FROM_SUB = 8;		// B
			public static final byte KEY_EC_SECP_256_R1 = 1;		// B
			public static final byte KEY_EC_SECP_384_R1 = 2;		// B
			public static final byte KEY_EC_SECP_521_R1 = 3;		// B
			public static final byte KEY_EC_SECP_256_K1 = 4;		// B
			public static final byte KEY_EC_BRAINPOOL_256_R1 = 5;		// B
			public static final byte KEY_EC_BRAINPOOL_384_R1 = 6;		// B
			public static final byte KEY_EC_BRAINPOOL_512_R1 = 7;		// B
			public static final short SW_NOT_SET = 28609;		// S
			public static final short SW_FAILED_SET = 28610;		// S
			public static final short SW_UNKNOWN_KEY_TYPE = 28611;		// S
		}

		.publicMethodTable 7 {
			equals(Ljava/lang/Object;)Z;
			register()V;
			register([BSB)V;
			selectingApplet()Z;
			deselect()V;
			getShareableInterfaceObject(Ljavacard/framework/AID;B)Ljavacard/framework/Shareable;;
			select()Z;
			process(Ljavacard/framework/APDU;)V;
			javaVMTests(Ljavacard/framework/APDU;[B)V;
			javaInstanceOfTest()B;
			buildPreciseKey(Ljavacard/security/Key;BS)Ljavacard/security/Key;;
			getKey(Ljavacard/security/Key;B[BS)S;
			getKeyInstance(Ljavacard/security/Key;)V;
			getCipherInstance()V;
			getSignerInstance()V;
			getKeyAgreementInstance()V;
			setKey(Ljavacard/framework/APDU;[B)V;
			encrypt(Ljavacard/framework/APDU;[B)V;
			decrypt(Ljavacard/framework/APDU;[B)V;
			derive(Ljavacard/framework/APDU;[B)V;
			sign(Ljavacard/framework/APDU;[B)V;
			verify(Ljavacard/framework/APDU;[B)V;
			setData(Ljavacard/framework/APDU;[B)V;
			doHash(Ljavacard/framework/APDU;[B)V;
			setKey(Ljavacard/security/Key;BB[BSS)Z;
			initECCurveParameters(Ljavacard/security/ECKey;B)Z;
		}

		.packageMethodTable 0 {
		}

		.method public static install([BSB)V 0 {
			.stack 1;
			.locals 0;

				L0:	new 43;		// jcostest/JCOSTestApplet
					invokespecial 44;		// jcostest/JCOSTestApplet.<init>()V
					return;
		}

		.method protected <init>()V 1 {
			.stack 3;
			.locals 0;

				L0:	aload_0;
					invokespecial 45;		// javacard/framework/Applet.<init>()V
					aload_0;
					aconst_null;
					putfield_a 0;		// reference jcostest/JCOSTestApplet.md
					aload_0;
					aconst_null;
					putfield_a 1;		// reference jcostest/JCOSTestApplet.signer
					aload_0;
					aconst_null;
					putfield_a 2;		// reference jcostest/JCOSTestApplet.cipher
					aload_0;
					aconst_null;
					putfield_a 3;		// reference jcostest/JCOSTestApplet.ka
					aload_0;
					aconst_null;
					putfield_a 4;		// reference jcostest/JCOSTestApplet.testKey1
					aload_0;
					aconst_null;
					putfield_a 5;		// reference jcostest/JCOSTestApplet.testKey2
					aload_0;
					aconst_null;
					putfield_a 6;		// reference jcostest/JCOSTestApplet.testKey3
					aload_0;
					aconst_null;
					putfield_a 7;		// reference jcostest/JCOSTestApplet.testKey4
					aload_0;
					aconst_null;
					putfield_a 8;		// reference jcostest/JCOSTestApplet.testKeyPair1
					aload_0;
					aconst_null;
					putfield_a 9;		// reference jcostest/JCOSTestApplet.testKeyPair2
					aload_0;
					sconst_0;
					putfield_b 10;		// byte jcostest/JCOSTestApplet.testKey1Type
					aload_0;
					sconst_0;
					putfield_b 11;		// byte jcostest/JCOSTestApplet.testKey2Type
					aload_0;
					sconst_0;
					putfield_b 12;		// byte jcostest/JCOSTestApplet.testKey3Type
					aload_0;
					sconst_0;
					putfield_b 13;		// byte jcostest/JCOSTestApplet.testKey4Type
					aload_0;
					sconst_0;
					putfield_b 14;		// byte jcostest/JCOSTestApplet.testKey1PersistentType
					aload_0;
					sconst_0;
					putfield_b 15;		// byte jcostest/JCOSTestApplet.testKey2PersistentType
					aload_0;
					sconst_0;
					putfield_b 16;		// byte jcostest/JCOSTestApplet.testKey3PersistentType
					aload_0;
					sconst_0;
					putfield_b 17;		// byte jcostest/JCOSTestApplet.testKey4PersistentType
					aload_0;
					aconst_null;
					putfield_a 18;		// reference jcostest/JCOSTestApplet.arbitraryData
					aload_0;
					sspush 256;
					sconst_1;
					invokestatic 65;		// javacard/framework/JCSystem.makeTransientByteArray(SB)[B
					putfield_a 19;		// reference jcostest/JCOSTestApplet.b0
					aload_0;
					sspush 255;
					sconst_1;
					invokestatic 65;		// javacard/framework/JCSystem.makeTransientByteArray(SB)[B
					putfield_a 20;		// reference jcostest/JCOSTestApplet.b1
					aload_0;
					invokevirtual 68;		// register()V
					return;
		}

		.method public process(Ljavacard/framework/APDU;)V 7 {
			.stack 5;
			.locals 4;

			.descriptor	Ljavacard/framework/APDU;	2.10;

				L0:	aload_0;
					invokevirtual 69;		// selectingApplet()Z
					ifeq L2;
				L1:	return;
				L2:	aload_1;
					invokevirtual 70;		// getBuffer()[B
					astore_2;
				L3:	aload_2;
					sconst_1;
					baload;
					sstore_3;
				L4:	sload_3;
					stableswitch L30 -16 11 L26 L27 L28 L29 L30 L30 L30 L30 L30 L30 L30 L30 L30 L30 L30 L30 L30 L5 L6 L7 L30 L19 L20 L21 L22 L23 L24 L25;
				L5:	aload_0;
					aload_1;
					aload_2;
					invokevirtual 71;		// setKey(Ljavacard/framework/APDU;[B)V
					goto_w L31;
				L6:	aload_0;
					aload_1;
					aload_2;
					invokevirtual 72;		// setData(Ljavacard/framework/APDU;[B)V
					goto_w L31;
				L7:	sconst_0;
					sstore 4;
				L8:	aload_2;
					sconst_3;
					baload;
					sstore 5;
				L9:	sload 5;
					sconst_1;
					if_scmpne L11;
				L10:	aload_0;
					getfield_a_this 4;		// reference jcostest/JCOSTestApplet.testKey1
					getfield_b_this 14;		// byte jcostest/JCOSTestApplet.testKey1PersistentType
					aload_2;
					sconst_0;
					invokevirtual 73;		// getKey(Ljavacard/security/Key;B[BS)S
					sstore 4;
					goto L18;
				L11:	sload 5;
					sconst_2;
					if_scmpne L13;
				L12:	aload_0;
					getfield_a_this 5;		// reference jcostest/JCOSTestApplet.testKey2
					getfield_b_this 15;		// byte jcostest/JCOSTestApplet.testKey2PersistentType
					aload_2;
					sconst_0;
					invokevirtual 73;		// getKey(Ljavacard/security/Key;B[BS)S
					sstore 4;
					goto L18;
				L13:	sload 5;
					sconst_3;
					if_scmpne L15;
				L14:	aload_0;
					getfield_a_this 6;		// reference jcostest/JCOSTestApplet.testKey3
					getfield_b_this 16;		// byte jcostest/JCOSTestApplet.testKey3PersistentType
					aload_2;
					sconst_0;
					invokevirtual 73;		// getKey(Ljavacard/security/Key;B[BS)S
					sstore 4;
					goto L18;
				L15:	sload 5;
					sconst_4;
					if_scmpne L17;
				L16:	aload_0;
					getfield_a_this 7;		// reference jcostest/JCOSTestApplet.testKey4
					getfield_b_this 17;		// byte jcostest/JCOSTestApplet.testKey4PersistentType
					aload_2;
					sconst_0;
					invokevirtual 73;		// getKey(Ljavacard/security/Key;B[BS)S
					sstore 4;
					goto L18;
				L17:	sspush 27267;
					invokestatic 74;		// javacard/framework/ISOException.throwIt(S)V
				L18:	aload_1;
					sconst_0;
					sload 4;
					invokevirtual 75;		// setOutgoingAndSend(SS)V
					goto L31;
				L19:	aload_0;
					aload_1;
					aload_2;
					invokevirtual 76;		// encrypt(Ljavacard/framework/APDU;[B)V
					goto L31;
				L20:	aload_0;
					aload_1;
					aload_2;
					invokevirtual 77;		// decrypt(Ljavacard/framework/APDU;[B)V
					goto L31;
				L21:	aload_0;
					aload_1;
					aload_2;
					invokevirtual 78;		// derive(Ljavacard/framework/APDU;[B)V
					goto L31;
				L22:	aload_0;
					aload_1;
					aload_2;
					invokevirtual 79;		// doHash(Ljavacard/framework/APDU;[B)V
					goto L31;
				L23:	aload_0;
					aload_1;
					aload_2;
					invokevirtual 80;		// sign(Ljavacard/framework/APDU;[B)V
					goto L31;
				L24:	aload_0;
					aload_1;
					aload_2;
					invokevirtual 81;		// verify(Ljavacard/framework/APDU;[B)V
					goto L31;
				L25:	aload_0;
					aload_1;
					aload_2;
					invokevirtual 82;		// javaVMTests(Ljavacard/framework/APDU;[B)V
					goto L31;
				L26:	aload_0;
					getfield_a_this 4;		// reference jcostest/JCOSTestApplet.testKey1
					invokevirtual 83;		// getKeyInstance(Ljavacard/security/Key;)V
					goto L31;
				L27:	aload_0;
					invokevirtual 84;		// getCipherInstance()V
					goto L31;
				L28:	aload_0;
					invokevirtual 85;		// getSignerInstance()V
					goto L31;
				L29:	aload_0;
					invokevirtual 86;		// getKeyAgreementInstance()V
					goto L31;
				L30:	sspush 27904;
					invokestatic 74;		// javacard/framework/ISOException.throwIt(S)V
				L31:	return;
		}

		.method public javaVMTests(Ljavacard/framework/APDU;[B)V 8 {
			.stack 3;
			.locals 2;

			.descriptor	Ljavacard/framework/APDU;	2.10;

				L0:	aload_2;
					sconst_2;
					baload;
					sstore_3;
				L1:	aload_2;
					sconst_3;
					baload;
					sstore 4;
				L2:	sload_3;
					stableswitch L4 1 1 L3;
				L3:	aload_2;
					sconst_0;
					aload_0;
					invokevirtual 87;		// javaInstanceOfTest()B
					bastore;
					aload_1;
					sconst_0;
					sconst_1;
					invokevirtual 75;		// setOutgoingAndSend(SS)V
					goto L5;
				L4:	sspush 27270;
					invokestatic 74;		// javacard/framework/ISOException.throwIt(S)V
				L5:	return;
		}

		.method public javaInstanceOfTest()B 9 {
			.stack 4;
			.locals 0;

				L0:	getfield_a_this 7;		// reference jcostest/JCOSTestApplet.testKey4
					ifnull L2;
				L1:	getfield_a_this 7;		// reference jcostest/JCOSTestApplet.testKey4
					invokeinterface 1 88 0;		// javacard/security/Key
				L2:	aload_0;
					bspush 15;
					sspush 256;
					sconst_0;
					invokestatic 89;		// javacard/security/KeyBuilder.buildKey(BSZ)Ljavacard/security/Key;
					checkcast 0 47;		// T_CLASSORINTERFACE javacard/security/AESKey
					putfield_a 7;		// reference jcostest/JCOSTestApplet.testKey4
					aload_0;
					sconst_0;
					putfield_b 13;		// byte jcostest/JCOSTestApplet.testKey4Type
					getfield_a_this 7;		// reference jcostest/JCOSTestApplet.testKey4
					instanceof 0 48;		// T_CLASSORINTERFACE javacard/security/DESKey
					ifeq L4;
				L3:	sconst_1;
					sreturn;
				L4:	getfield_a_this 7;		// reference jcostest/JCOSTestApplet.testKey4
					instanceof 0 47;		// T_CLASSORINTERFACE javacard/security/AESKey
					ifeq L6;
				L5:	sconst_2;
					sreturn;
				L6:	getfield_a_this 7;		// reference jcostest/JCOSTestApplet.testKey4
					instanceof 0 90;		// T_CLASSORINTERFACE javacard/security/RSAPrivateKey
					ifeq L8;
				L7:	sconst_3;
					sreturn;
				L8:	getfield_a_this 7;		// reference jcostest/JCOSTestApplet.testKey4
					instanceof 0 91;		// T_CLASSORINTERFACE javacard/security/RSAPublicKey
					ifeq L10;
				L9:	sconst_4;
					sreturn;
				L10:	getfield_a_this 7;		// reference jcostest/JCOSTestApplet.testKey4
					instanceof 0 51;		// T_CLASSORINTERFACE javacard/security/ECPrivateKey
					ifeq L12;
				L11:	sconst_5;
					sreturn;
				L12:	getfield_a_this 7;		// reference jcostest/JCOSTestApplet.testKey4
					instanceof 0 49;		// T_CLASSORINTERFACE javacard/security/ECPublicKey
					ifeq L14;
				L13:	bspush 6;
					sreturn;
				L14:	sconst_m1;
					sreturn;
		}

		.method public buildPreciseKey(Ljavacard/security/Key;BS)Ljavacard/security/Key; 10 {
			.stack 3;
			.locals 0;

			.descriptor	Ljavacard/security/Key;	1.0;
			.descriptor	Ljavacard/security/Key;	1.0;

				L0:	sload_2;
					slookupswitch L11 10 1 L6 2 L5 3 L4 11 L10 12 L7 13 L3 14 L2 15 L1 30 L9 31 L8;
				L1:	sload_2;
					sload_3;
					sconst_0;
					invokestatic 89;		// javacard/security/KeyBuilder.buildKey(BSZ)Ljavacard/security/Key;
					checkcast 0 47;		// T_CLASSORINTERFACE javacard/security/AESKey
					astore_1;
					goto L11;
				L2:	sload_2;
					sload_3;
					sconst_0;
					invokestatic 89;		// javacard/security/KeyBuilder.buildKey(BSZ)Ljavacard/security/Key;
					checkcast 0 47;		// T_CLASSORINTERFACE javacard/security/AESKey
					astore_1;
					goto L11;
				L3:	sload_2;
					sload_3;
					sconst_0;
					invokestatic 89;		// javacard/security/KeyBuilder.buildKey(BSZ)Ljavacard/security/Key;
					checkcast 0 47;		// T_CLASSORINTERFACE javacard/security/AESKey
					astore_1;
					goto L11;
				L4:	sload_2;
					sload_3;
					sconst_0;
					invokestatic 89;		// javacard/security/KeyBuilder.buildKey(BSZ)Ljavacard/security/Key;
					checkcast 0 48;		// T_CLASSORINTERFACE javacard/security/DESKey
					astore_1;
					goto L11;
				L5:	sload_2;
					sload_3;
					sconst_0;
					invokestatic 89;		// javacard/security/KeyBuilder.buildKey(BSZ)Ljavacard/security/Key;
					checkcast 0 48;		// T_CLASSORINTERFACE javacard/security/DESKey
					astore_1;
					goto L11;
				L6:	sload_2;
					sload_3;
					sconst_0;
					invokestatic 89;		// javacard/security/KeyBuilder.buildKey(BSZ)Ljavacard/security/Key;
					checkcast 0 48;		// T_CLASSORINTERFACE javacard/security/DESKey
					astore_1;
					goto L11;
				L7:	sload_2;
					sload_3;
					sconst_0;
					invokestatic 89;		// javacard/security/KeyBuilder.buildKey(BSZ)Ljavacard/security/Key;
					checkcast 0 51;		// T_CLASSORINTERFACE javacard/security/ECPrivateKey
					astore_1;
					goto L11;
				L8:	sload_2;
					sload_3;
					sconst_0;
					invokestatic 89;		// javacard/security/KeyBuilder.buildKey(BSZ)Ljavacard/security/Key;
					checkcast 0 51;		// T_CLASSORINTERFACE javacard/security/ECPrivateKey
					astore_1;
					goto L11;
				L9:	sload_2;
					sload_3;
					sconst_0;
					invokestatic 89;		// javacard/security/KeyBuilder.buildKey(BSZ)Ljavacard/security/Key;
					checkcast 0 51;		// T_CLASSORINTERFACE javacard/security/ECPrivateKey
					astore_1;
					goto L11;
				L10:	sload_2;
					sload_3;
					sconst_0;
					invokestatic 89;		// javacard/security/KeyBuilder.buildKey(BSZ)Ljavacard/security/Key;
					checkcast 0 49;		// T_CLASSORINTERFACE javacard/security/ECPublicKey
					astore_1;
					goto L11;
				L11:	aload_1;
					ifnonnull L13;
				L12:	sspush 25088;
					invokestatic 74;		// javacard/framework/ISOException.throwIt(S)V
				L13:	aload_1;
					areturn;
		}

		.method public getKey(Ljavacard/security/Key;B[BS)S 11 {
			.stack 3;
			.locals 1;

			.descriptor	Ljavacard/security/Key;	1.0;

				L0:	sconst_0;
					sstore 5;
				L1:	getfield_a_this 4;		// reference jcostest/JCOSTestApplet.testKey1
					ifnonnull L3;
				L2:	sspush 28609;
					invokestatic 74;		// javacard/framework/ISOException.throwIt(S)V
				L3:	getfield_a_this 4;		// reference jcostest/JCOSTestApplet.testKey1
					invokeinterface 1 88 3;		// javacard/security/Key
					ifne L5;
				L4:	sspush 28609;
					invokestatic 74;		// javacard/framework/ISOException.throwIt(S)V
				L5:	sload_2;
					slookupswitch L16 10 1 L11 2 L10 3 L9 11 L15 12 L12 13 L8 14 L7 15 L6 30 L14 31 L13;
				L6:	aload_1;
					checkcast 0 47;		// T_CLASSORINTERFACE javacard/security/AESKey
					aload_3;
					sload 4;
					invokeinterface 3 47 5;		// javacard/security/AESKey
					sstore 5;
					goto_w L16;
				L7:	aload_1;
					checkcast 0 47;		// T_CLASSORINTERFACE javacard/security/AESKey
					aload_3;
					sload 4;
					invokeinterface 3 47 5;		// javacard/security/AESKey
					sstore 5;
					goto_w L16;
				L8:	aload_1;
					checkcast 0 47;		// T_CLASSORINTERFACE javacard/security/AESKey
					aload_3;
					sload 4;
					invokeinterface 3 47 5;		// javacard/security/AESKey
					sstore 5;
					goto L16;
				L9:	aload_1;
					checkcast 0 48;		// T_CLASSORINTERFACE javacard/security/DESKey
					aload_3;
					sload 4;
					invokeinterface 3 48 4;		// javacard/security/DESKey
					sstore 5;
					goto L16;
				L10:	aload_1;
					checkcast 0 48;		// T_CLASSORINTERFACE javacard/security/DESKey
					aload_3;
					sload 4;
					invokeinterface 3 48 4;		// javacard/security/DESKey
					sstore 5;
					goto L16;
				L11:	aload_1;
					checkcast 0 48;		// T_CLASSORINTERFACE javacard/security/DESKey
					aload_3;
					sload 4;
					invokeinterface 3 48 4;		// javacard/security/DESKey
					sstore 5;
					goto L16;
				L12:	aload_1;
					checkcast 0 51;		// T_CLASSORINTERFACE javacard/security/ECPrivateKey
					aload_3;
					sload 4;
					invokeinterface 3 51 19;		// javacard/security/ECPrivateKey
					sstore 5;
					goto L16;
				L13:	aload_1;
					checkcast 0 51;		// T_CLASSORINTERFACE javacard/security/ECPrivateKey
					aload_3;
					sload 4;
					invokeinterface 3 51 19;		// javacard/security/ECPrivateKey
					sstore 5;
					goto L16;
				L14:	aload_1;
					checkcast 0 51;		// T_CLASSORINTERFACE javacard/security/ECPrivateKey
					aload_3;
					sload 4;
					invokeinterface 3 51 19;		// javacard/security/ECPrivateKey
					sstore 5;
					goto L16;
				L15:	aload_1;
					checkcast 0 49;		// T_CLASSORINTERFACE javacard/security/ECPublicKey
					aload_3;
					sload 4;
					invokeinterface 3 49 19;		// javacard/security/ECPublicKey
					sstore 5;
					goto L16;
				L16:	sload 5;
					sreturn;
		}

		.method public getKeyInstance(Ljavacard/security/Key;)V 12 {
			.stack 2;
			.locals 0;

			.descriptor	Ljavacard/security/Key;	1.0;

				L0:	getfield_a_this 4;		// reference jcostest/JCOSTestApplet.testKey1
					ifnonnull L2;
				L1:	sspush 28609;
					invokestatic 74;		// javacard/framework/ISOException.throwIt(S)V
				L2:	getfield_a_this 4;		// reference jcostest/JCOSTestApplet.testKey1
					invokeinterface 1 88 3;		// javacard/security/Key
					ifne L4;
				L3:	sspush 28609;
					invokestatic 74;		// javacard/framework/ISOException.throwIt(S)V
				L4:	aload_1;
					instanceof 0 47;		// T_CLASSORINTERFACE javacard/security/AESKey
					ifeq L6;
				L5:	bspush 106;
					bspush -31;
					invokestatic 92;		// javacard/framework/Util.makeShort(BB)S
					invokestatic 74;		// javacard/framework/ISOException.throwIt(S)V
					goto L17;
				L6:	aload_1;
					instanceof 0 48;		// T_CLASSORINTERFACE javacard/security/DESKey
					ifeq L8;
				L7:	bspush 106;
					bspush -30;
					invokestatic 92;		// javacard/framework/Util.makeShort(BB)S
					invokestatic 74;		// javacard/framework/ISOException.throwIt(S)V
					goto L17;
				L8:	aload_1;
					instanceof 0 90;		// T_CLASSORINTERFACE javacard/security/RSAPrivateKey
					ifeq L10;
				L9:	bspush 106;
					bspush -29;
					invokestatic 92;		// javacard/framework/Util.makeShort(BB)S
					invokestatic 74;		// javacard/framework/ISOException.throwIt(S)V
					goto L17;
				L10:	aload_1;
					instanceof 0 91;		// T_CLASSORINTERFACE javacard/security/RSAPublicKey
					ifeq L12;
				L11:	bspush 106;
					bspush -28;
					invokestatic 92;		// javacard/framework/Util.makeShort(BB)S
					invokestatic 74;		// javacard/framework/ISOException.throwIt(S)V
					goto L17;
				L12:	aload_1;
					instanceof 0 51;		// T_CLASSORINTERFACE javacard/security/ECPrivateKey
					ifeq L14;
				L13:	bspush 106;
					bspush -27;
					invokestatic 92;		// javacard/framework/Util.makeShort(BB)S
					invokestatic 74;		// javacard/framework/ISOException.throwIt(S)V
					goto L17;
				L14:	aload_1;
					instanceof 0 49;		// T_CLASSORINTERFACE javacard/security/ECPublicKey
					ifeq L16;
				L15:	bspush 106;
					bspush -26;
					invokestatic 92;		// javacard/framework/Util.makeShort(BB)S
					invokestatic 74;		// javacard/framework/ISOException.throwIt(S)V
					goto L17;
				L16:	bspush 106;
					sconst_m1;
					invokestatic 92;		// javacard/framework/Util.makeShort(BB)S
					invokestatic 74;		// javacard/framework/ISOException.throwIt(S)V
				L17:	return;
		}

		.method public getCipherInstance()V 13 {
			.stack 2;
			.locals 0;

				L0:	getfield_a_this 2;		// reference jcostest/JCOSTestApplet.cipher
					ifnonnull L2;
				L1:	sspush 28609;
					invokestatic 74;		// javacard/framework/ISOException.throwIt(S)V
				L2:	bspush 106;
					getfield_a_this 2;		// reference jcostest/JCOSTestApplet.cipher
					invokevirtual 93;		// getAlgorithm()B
					invokestatic 92;		// javacard/framework/Util.makeShort(BB)S
					invokestatic 74;		// javacard/framework/ISOException.throwIt(S)V
					return;
		}

		.method public getSignerInstance()V 14 {
			.stack 2;
			.locals 0;

				L0:	getfield_a_this 1;		// reference jcostest/JCOSTestApplet.signer
					ifnonnull L2;
				L1:	sspush 28609;
					invokestatic 74;		// javacard/framework/ISOException.throwIt(S)V
				L2:	bspush 106;
					getfield_a_this 1;		// reference jcostest/JCOSTestApplet.signer
					invokevirtual 94;		// getAlgorithm()B
					invokestatic 92;		// javacard/framework/Util.makeShort(BB)S
					invokestatic 74;		// javacard/framework/ISOException.throwIt(S)V
					return;
		}

		.method public getKeyAgreementInstance()V 15 {
			.stack 2;
			.locals 0;

				L0:	getfield_a_this 3;		// reference jcostest/JCOSTestApplet.ka
					ifnonnull L2;
				L1:	sspush 28609;
					invokestatic 74;		// javacard/framework/ISOException.throwIt(S)V
				L2:	bspush 106;
					getfield_a_this 3;		// reference jcostest/JCOSTestApplet.ka
					invokevirtual 95;		// getAlgorithm()B
					invokestatic 92;		// javacard/framework/Util.makeShort(BB)S
					invokestatic 74;		// javacard/framework/ISOException.throwIt(S)V
					return;
		}

		.method public setKey(Ljavacard/framework/APDU;[B)V 16 {
			.stack 7;
			.locals 3;

			.descriptor	Ljavacard/framework/APDU;	2.10;

				L0:	aload_1;
					invokevirtual 96;		// setIncomingAndReceive()S
					sstore_3;
				L1:	aload_2;
					sconst_2;
					baload;
					sstore 4;
				L2:	aload_2;
					sconst_3;
					baload;
					sstore 5;
				L3:	sload 4;
					stableswitch L84 1 8 L4 L74 L61 L84 L84 L84 L23 L44;
				L4:	sload_3;
					sconst_4;
					if_scmpeq L6;
				L5:	sspush 26368;
					invokestatic 74;		// javacard/framework/ISOException.throwIt(S)V
				L6:	aload_2;
					aload_1;
					invokevirtual 97;		// getOffsetCdata()S
					baload;
					aload_2;
					aload_1;
					invokevirtual 97;		// getOffsetCdata()S
					sconst_1;
					sadd;
					baload;
					invokestatic 92;		// javacard/framework/Util.makeShort(BB)S
					sstore_3;
					getfield_a_this 19;		// reference jcostest/JCOSTestApplet.b0
					sconst_0;
					getfield_a_this 19;		// reference jcostest/JCOSTestApplet.b0
					arraylength;
					sconst_0;
					invokestatic 98;		// javacard/framework/Util.arrayFillNonAtomic([BSSB)S
					pop;
					sload 5;
					sconst_1;
					if_scmpne L10;
				L7:	getfield_a_this 4;		// reference jcostest/JCOSTestApplet.testKey1
					ifnull L9;
				L8:	getfield_a_this 4;		// reference jcostest/JCOSTestApplet.testKey1
					invokeinterface 1 88 0;		// javacard/security/Key
				L9:	aload_0;
					aload_2;
					aload_1;
					invokevirtual 97;		// getOffsetCdata()S
					sconst_3;
					sadd;
					baload;
					putfield_b 14;		// byte jcostest/JCOSTestApplet.testKey1PersistentType
					aload_0;
					aload_0;
					getfield_a_this 4;		// reference jcostest/JCOSTestApplet.testKey1
					getfield_b_this 14;		// byte jcostest/JCOSTestApplet.testKey1PersistentType
					sload_3;
					invokevirtual 99;		// buildPreciseKey(Ljavacard/security/Key;BS)Ljavacard/security/Key;
					putfield_a 4;		// reference jcostest/JCOSTestApplet.testKey1
					aload_0;
					aload_2;
					aload_1;
					invokevirtual 97;		// getOffsetCdata()S
					sconst_2;
					sadd;
					baload;
					putfield_b 10;		// byte jcostest/JCOSTestApplet.testKey1Type
					goto_w L85;
				L10:	sload 5;
					sconst_2;
					if_scmpne L14;
				L11:	getfield_a_this 5;		// reference jcostest/JCOSTestApplet.testKey2
					ifnull L13;
				L12:	getfield_a_this 5;		// reference jcostest/JCOSTestApplet.testKey2
					invokeinterface 1 88 0;		// javacard/security/Key
				L13:	aload_0;
					aload_2;
					aload_1;
					invokevirtual 97;		// getOffsetCdata()S
					sconst_3;
					sadd;
					baload;
					putfield_b 15;		// byte jcostest/JCOSTestApplet.testKey2PersistentType
					aload_0;
					aload_0;
					getfield_a_this 5;		// reference jcostest/JCOSTestApplet.testKey2
					getfield_b_this 15;		// byte jcostest/JCOSTestApplet.testKey2PersistentType
					sload_3;
					invokevirtual 99;		// buildPreciseKey(Ljavacard/security/Key;BS)Ljavacard/security/Key;
					putfield_a 5;		// reference jcostest/JCOSTestApplet.testKey2
					aload_0;
					aload_2;
					aload_1;
					invokevirtual 97;		// getOffsetCdata()S
					sconst_2;
					sadd;
					baload;
					putfield_b 11;		// byte jcostest/JCOSTestApplet.testKey2Type
					goto_w L85;
				L14:	sload 5;
					sconst_3;
					if_scmpne L18;
				L15:	getfield_a_this 6;		// reference jcostest/JCOSTestApplet.testKey3
					ifnull L17;
				L16:	getfield_a_this 6;		// reference jcostest/JCOSTestApplet.testKey3
					invokeinterface 1 88 0;		// javacard/security/Key
				L17:	aload_0;
					aload_2;
					aload_1;
					invokevirtual 97;		// getOffsetCdata()S
					sconst_3;
					sadd;
					baload;
					putfield_b 16;		// byte jcostest/JCOSTestApplet.testKey3PersistentType
					aload_0;
					aload_0;
					getfield_a_this 6;		// reference jcostest/JCOSTestApplet.testKey3
					getfield_b_this 16;		// byte jcostest/JCOSTestApplet.testKey3PersistentType
					sload_3;
					invokevirtual 99;		// buildPreciseKey(Ljavacard/security/Key;BS)Ljavacard/security/Key;
					putfield_a 6;		// reference jcostest/JCOSTestApplet.testKey3
					aload_0;
					aload_2;
					aload_1;
					invokevirtual 97;		// getOffsetCdata()S
					sconst_2;
					sadd;
					baload;
					putfield_b 12;		// byte jcostest/JCOSTestApplet.testKey3Type
					goto_w L85;
				L18:	sload 5;
					sconst_4;
					if_scmpne L22;
				L19:	getfield_a_this 7;		// reference jcostest/JCOSTestApplet.testKey4
					ifnull L21;
				L20:	getfield_a_this 7;		// reference jcostest/JCOSTestApplet.testKey4
					invokeinterface 1 88 0;		// javacard/security/Key
				L21:	aload_0;
					aload_2;
					aload_1;
					invokevirtual 97;		// getOffsetCdata()S
					sconst_3;
					sadd;
					baload;
					putfield_b 17;		// byte jcostest/JCOSTestApplet.testKey4PersistentType
					aload_0;
					aload_0;
					getfield_a_this 7;		// reference jcostest/JCOSTestApplet.testKey4
					getfield_b_this 17;		// byte jcostest/JCOSTestApplet.testKey4PersistentType
					sload_3;
					invokevirtual 99;		// buildPreciseKey(Ljavacard/security/Key;BS)Ljavacard/security/Key;
					putfield_a 7;		// reference jcostest/JCOSTestApplet.testKey4
					aload_0;
					aload_2;
					aload_1;
					invokevirtual 97;		// getOffsetCdata()S
					sconst_2;
					sadd;
					baload;
					putfield_b 13;		// byte jcostest/JCOSTestApplet.testKey4Type
					goto_w L85;
				L22:	sspush 27267;
					invokestatic 74;		// javacard/framework/ISOException.throwIt(S)V
					goto_w L85;
				L23:	sload 5;
					sconst_1;
					if_scmpne L28;
				L24:	getfield_a_this 4;		// reference jcostest/JCOSTestApplet.testKey1
					ifnonnull L26;
				L25:	sspush 28609;
					invokestatic 74;		// javacard/framework/ISOException.throwIt(S)V
				L26:	aload_0;
					getfield_a_this 4;		// reference jcostest/JCOSTestApplet.testKey1
					getfield_b_this 10;		// byte jcostest/JCOSTestApplet.testKey1Type
					getfield_b_this 14;		// byte jcostest/JCOSTestApplet.testKey1PersistentType
					aload_2;
					aload_1;
					invokevirtual 97;		// getOffsetCdata()S
					sload_3;
					invokevirtual 100;		// setKey(Ljavacard/security/Key;BB[BSS)Z
					ifne_w L85;
				L27:	sspush 28610;
					invokestatic 74;		// javacard/framework/ISOException.throwIt(S)V
					goto_w L85;
				L28:	sload 5;
					sconst_2;
					if_scmpne L33;
				L29:	getfield_a_this 5;		// reference jcostest/JCOSTestApplet.testKey2
					ifnonnull L31;
				L30:	sspush 28609;
					invokestatic 74;		// javacard/framework/ISOException.throwIt(S)V
				L31:	aload_0;
					getfield_a_this 5;		// reference jcostest/JCOSTestApplet.testKey2
					getfield_b_this 11;		// byte jcostest/JCOSTestApplet.testKey2Type
					getfield_b_this 15;		// byte jcostest/JCOSTestApplet.testKey2PersistentType
					aload_2;
					aload_1;
					invokevirtual 97;		// getOffsetCdata()S
					sload_3;
					invokevirtual 100;		// setKey(Ljavacard/security/Key;BB[BSS)Z
					ifne_w L85;
				L32:	sspush 28610;
					invokestatic 74;		// javacard/framework/ISOException.throwIt(S)V
					goto_w L85;
				L33:	sload 5;
					sconst_3;
					if_scmpne L38;
				L34:	getfield_a_this 6;		// reference jcostest/JCOSTestApplet.testKey3
					ifnonnull L36;
				L35:	sspush 28609;
					invokestatic 74;		// javacard/framework/ISOException.throwIt(S)V
				L36:	aload_0;
					getfield_a_this 6;		// reference jcostest/JCOSTestApplet.testKey3
					getfield_b_this 12;		// byte jcostest/JCOSTestApplet.testKey3Type
					getfield_b_this 16;		// byte jcostest/JCOSTestApplet.testKey3PersistentType
					aload_2;
					aload_1;
					invokevirtual 97;		// getOffsetCdata()S
					sload_3;
					invokevirtual 100;		// setKey(Ljavacard/security/Key;BB[BSS)Z
					ifne_w L85;
				L37:	sspush 28610;
					invokestatic 74;		// javacard/framework/ISOException.throwIt(S)V
					goto_w L85;
				L38:	sload 5;
					sconst_4;
					if_scmpne L43;
				L39:	getfield_a_this 7;		// reference jcostest/JCOSTestApplet.testKey4
					ifnonnull L41;
				L40:	sspush 28609;
					invokestatic 74;		// javacard/framework/ISOException.throwIt(S)V
				L41:	aload_0;
					getfield_a_this 7;		// reference jcostest/JCOSTestApplet.testKey4
					getfield_b_this 13;		// byte jcostest/JCOSTestApplet.testKey4Type
					getfield_b_this 17;		// byte jcostest/JCOSTestApplet.testKey4PersistentType
					aload_2;
					aload_1;
					invokevirtual 97;		// getOffsetCdata()S
					sload_3;
					invokevirtual 100;		// setKey(Ljavacard/security/Key;BB[BSS)Z
					ifne_w L85;
				L42:	sspush 28610;
					invokestatic 74;		// javacard/framework/ISOException.throwIt(S)V
					goto_w L85;
				L43:	sspush 27267;
					invokestatic 74;		// javacard/framework/ISOException.throwIt(S)V
					goto_w L85;
				L44:	sload 5;
					sconst_1;
					if_scmpne L48;
				L45:	getfield_a_this 4;		// reference jcostest/JCOSTestApplet.testKey1
					ifnonnull L47;
				L46:	sspush 28609;
					invokestatic 74;		// javacard/framework/ISOException.throwIt(S)V
				L47:	getfield_a_this 4;		// reference jcostest/JCOSTestApplet.testKey1
					getfield_b_this 10;		// byte jcostest/JCOSTestApplet.testKey1Type
					aload_2;
					aload_1;
					invokevirtual 97;		// getOffsetCdata()S
					sload_3;
					invokestatic 101;		// jcostest/AlternateKM.setKey(Ljavacard/security/Key;B[BSS)Z
					pop;
					goto_w L85;
				L48:	sload 5;
					sconst_2;
					if_scmpne L52;
				L49:	getfield_a_this 5;		// reference jcostest/JCOSTestApplet.testKey2
					ifnonnull L51;
				L50:	sspush 28609;
					invokestatic 74;		// javacard/framework/ISOException.throwIt(S)V
				L51:	getfield_a_this 5;		// reference jcostest/JCOSTestApplet.testKey2
					getfield_b_this 11;		// byte jcostest/JCOSTestApplet.testKey2Type
					aload_2;
					aload_1;
					invokevirtual 97;		// getOffsetCdata()S
					sload_3;
					invokestatic 101;		// jcostest/AlternateKM.setKey(Ljavacard/security/Key;B[BSS)Z
					pop;
					goto_w L85;
				L52:	sload 5;
					sconst_3;
					if_scmpne L56;
				L53:	getfield_a_this 6;		// reference jcostest/JCOSTestApplet.testKey3
					ifnonnull L55;
				L54:	sspush 28609;
					invokestatic 74;		// javacard/framework/ISOException.throwIt(S)V
				L55:	getfield_a_this 6;		// reference jcostest/JCOSTestApplet.testKey3
					getfield_b_this 12;		// byte jcostest/JCOSTestApplet.testKey3Type
					aload_2;
					aload_1;
					invokevirtual 97;		// getOffsetCdata()S
					sload_3;
					invokestatic 101;		// jcostest/AlternateKM.setKey(Ljavacard/security/Key;B[BSS)Z
					pop;
					goto_w L85;
				L56:	sload 5;
					sconst_4;
					if_scmpne L60;
				L57:	getfield_a_this 7;		// reference jcostest/JCOSTestApplet.testKey4
					ifnonnull L59;
				L58:	sspush 28609;
					invokestatic 74;		// javacard/framework/ISOException.throwIt(S)V
				L59:	getfield_a_this 7;		// reference jcostest/JCOSTestApplet.testKey4
					getfield_b_this 13;		// byte jcostest/JCOSTestApplet.testKey4Type
					aload_2;
					aload_1;
					invokevirtual 97;		// getOffsetCdata()S
					sload_3;
					invokestatic 101;		// jcostest/AlternateKM.setKey(Ljavacard/security/Key;B[BSS)Z
					pop;
					goto_w L85;
				L60:	sspush 27267;
					invokestatic 74;		// javacard/framework/ISOException.throwIt(S)V
					goto_w L85;
				L61:	sload 5;
					sconst_1;
					if_scmpne L64;
				L62:	getfield_a_this 4;		// reference jcostest/JCOSTestApplet.testKey1
					invokeinterface 1 88 3;		// javacard/security/Key
					ifne_w L85;
				L63:	sspush 28609;
					invokestatic 74;		// javacard/framework/ISOException.throwIt(S)V
					goto_w L85;
				L64:	sload 5;
					sconst_2;
					if_scmpne L67;
				L65:	getfield_a_this 5;		// reference jcostest/JCOSTestApplet.testKey2
					invokeinterface 1 88 3;		// javacard/security/Key
					ifne_w L85;
				L66:	sspush 28609;
					invokestatic 74;		// javacard/framework/ISOException.throwIt(S)V
					goto_w L85;
				L67:	sload 5;
					sconst_3;
					if_scmpne L70;
				L68:	getfield_a_this 6;		// reference jcostest/JCOSTestApplet.testKey3
					invokeinterface 1 88 3;		// javacard/security/Key
					ifne_w L85;
				L69:	sspush 28609;
					invokestatic 74;		// javacard/framework/ISOException.throwIt(S)V
					goto_w L85;
				L70:	sload 5;
					sconst_4;
					if_scmpne L73;
				L71:	getfield_a_this 7;		// reference jcostest/JCOSTestApplet.testKey4
					invokeinterface 1 88 3;		// javacard/security/Key
					ifne L85;
				L72:	sspush 28609;
					invokestatic 74;		// javacard/framework/ISOException.throwIt(S)V
					goto L85;
				L73:	sspush 27267;
					invokestatic 74;		// javacard/framework/ISOException.throwIt(S)V
					goto L85;
				L74:	sload 5;
					sconst_1;
					if_scmpne L76;
				L75:	aload_0;
					getfield_a_this 4;		// reference jcostest/JCOSTestApplet.testKey1
					getfield_b_this 14;		// byte jcostest/JCOSTestApplet.testKey1PersistentType
					aload_2;
					sconst_0;
					invokevirtual 73;		// getKey(Ljavacard/security/Key;B[BS)S
					sstore_3;
					goto L83;
				L76:	sload 5;
					sconst_2;
					if_scmpne L78;
				L77:	aload_0;
					getfield_a_this 5;		// reference jcostest/JCOSTestApplet.testKey2
					getfield_b_this 15;		// byte jcostest/JCOSTestApplet.testKey2PersistentType
					aload_2;
					sconst_0;
					invokevirtual 73;		// getKey(Ljavacard/security/Key;B[BS)S
					sstore_3;
					goto L83;
				L78:	sload 5;
					sconst_3;
					if_scmpne L80;
				L79:	aload_0;
					getfield_a_this 6;		// reference jcostest/JCOSTestApplet.testKey3
					getfield_b_this 16;		// byte jcostest/JCOSTestApplet.testKey3PersistentType
					aload_2;
					sconst_0;
					invokevirtual 73;		// getKey(Ljavacard/security/Key;B[BS)S
					sstore_3;
					goto L83;
				L80:	sload 5;
					sconst_4;
					if_scmpne L82;
				L81:	aload_0;
					getfield_a_this 7;		// reference jcostest/JCOSTestApplet.testKey4
					getfield_b_this 17;		// byte jcostest/JCOSTestApplet.testKey4PersistentType
					aload_2;
					sconst_0;
					invokevirtual 73;		// getKey(Ljavacard/security/Key;B[BS)S
					sstore_3;
					goto L83;
				L82:	sspush 27267;
					invokestatic 74;		// javacard/framework/ISOException.throwIt(S)V
				L83:	aload_1;
					sconst_0;
					sload_3;
					invokevirtual 75;		// setOutgoingAndSend(SS)V
					goto L85;
				L84:	sspush 27270;
					invokestatic 74;		// javacard/framework/ISOException.throwIt(S)V
				L85:	return;
		}

		.method public encrypt(Ljavacard/framework/APDU;[B)V 17 {
			.stack 6;
			.locals 5;

			.descriptor	Ljavacard/framework/APDU;	2.10;

				L0:	aload_1;
					invokevirtual 96;		// setIncomingAndReceive()S
					sstore_3;
				L1:	aload_2;
					sconst_2;
					baload;
					sstore 4;
				L2:	aload_2;
					sconst_3;
					baload;
					sstore 5;
				L3:	sload 4;
					stableswitch L57 1 6 L4 L57 L9 L12 L27 L42;
				L4:	aload_0;
					sload 5;
					sconst_0;
					invokestatic 103;		// javacardx/crypto/Cipher.getInstance(BZ)Ljavacardx/crypto/Cipher;
					putfield_a 2;		// reference jcostest/JCOSTestApplet.cipher
				L5:	goto_w L58;
				L6:	astore 6;
				L7:	sspush 27265;
					invokestatic 74;		// javacard/framework/ISOException.throwIt(S)V
				L8:	goto_w L58;
				L9:	getfield_a_this 2;		// reference jcostest/JCOSTestApplet.cipher
					ifnull L11;
				L10:	aload_2;
					sconst_0;
					getfield_a_this 2;		// reference jcostest/JCOSTestApplet.cipher
					invokevirtual 93;		// getAlgorithm()B
					bastore;
					aload_1;
					sconst_0;
					sconst_1;
					invokevirtual 75;		// setOutgoingAndSend(SS)V
					goto_w L58;
				L11:	sspush 25088;
					invokestatic 74;		// javacard/framework/ISOException.throwIt(S)V
					goto_w L58;
				L12:	aconst_null;
					astore 6;
				L13:	sload 5;
					sconst_1;
					if_scmpne L15;
				L14:	getfield_a_this 4;		// reference jcostest/JCOSTestApplet.testKey1
					astore 6;
					goto L22;
				L15:	sload 5;
					sconst_2;
					if_scmpne L17;
				L16:	getfield_a_this 5;		// reference jcostest/JCOSTestApplet.testKey2
					astore 6;
					goto L22;
				L17:	sload 5;
					sconst_3;
					if_scmpne L19;
				L18:	getfield_a_this 6;		// reference jcostest/JCOSTestApplet.testKey3
					astore 6;
					goto L22;
				L19:	sload 5;
					sconst_4;
					if_scmpne L21;
				L20:	getfield_a_this 7;		// reference jcostest/JCOSTestApplet.testKey4
					astore 6;
					goto L22;
				L21:	sspush 27267;
					invokestatic 74;		// javacard/framework/ISOException.throwIt(S)V
				L22:	aload 6;
					invokeinterface 1 88 3;		// javacard/security/Key
					ifeq L26;
				L23:	sload_3;
					ifgt L25;
				L24:	getfield_a_this 2;		// reference jcostest/JCOSTestApplet.cipher
					aload 6;
					sconst_2;
					invokevirtual 104;		// init(Ljavacard/security/Key;B)V
					goto_w L58;
				L25:	getfield_a_this 2;		// reference jcostest/JCOSTestApplet.cipher
					aload 6;
					sconst_2;
					aload_2;
					aload_1;
					invokevirtual 97;		// getOffsetCdata()S
					sload_3;
					invokevirtual 105;		// init(Ljavacard/security/Key;B[BSS)V
					goto_w L58;
				L26:	sspush 28609;
					invokestatic 74;		// javacard/framework/ISOException.throwIt(S)V
					goto_w L58;
				L27:	getfield_a_this 2;		// reference jcostest/JCOSTestApplet.cipher
					aload_2;
					aload_1;
					invokevirtual 97;		// getOffsetCdata()S
					sload_3;
					getfield_a_this 19;		// reference jcostest/JCOSTestApplet.b0
					sconst_0;
					invokevirtual 106;		// update([BSS[BS)S
					sstore 7;
				L28:	aload_1;
					invokevirtual 107;		// setOutgoing()S
					pop;
					aload_1;
					sload 7;
					invokevirtual 108;		// setOutgoingLength(S)V
					aload_1;
					getfield_a_this 19;		// reference jcostest/JCOSTestApplet.b0
					sconst_0;
					sload 7;
					invokevirtual 109;		// sendBytesLong([BSS)V
				L29:	goto_w L58;
				L30:	astore 7;
				L31:	aload 7;
					invokevirtual 110;		// getReason()S
					sconst_5;
					if_scmpne L33;
				L32:	bspush 105;
					sconst_1;
					invokestatic 92;		// javacard/framework/Util.makeShort(BB)S
					invokestatic 74;		// javacard/framework/ISOException.throwIt(S)V
					goto_w L58;
				L33:	aload 7;
					invokevirtual 110;		// getReason()S
					sconst_1;
					if_scmpne L35;
				L34:	bspush 105;
					sconst_2;
					invokestatic 92;		// javacard/framework/Util.makeShort(BB)S
					invokestatic 74;		// javacard/framework/ISOException.throwIt(S)V
					goto_w L58;
				L35:	aload 7;
					invokevirtual 110;		// getReason()S
					sconst_4;
					if_scmpne L37;
				L36:	bspush 105;
					sconst_3;
					invokestatic 92;		// javacard/framework/Util.makeShort(BB)S
					invokestatic 74;		// javacard/framework/ISOException.throwIt(S)V
					goto_w L58;
				L37:	aload 7;
					invokevirtual 110;		// getReason()S
					sconst_3;
					if_scmpne L39;
				L38:	bspush 105;
					sconst_4;
					invokestatic 92;		// javacard/framework/Util.makeShort(BB)S
					invokestatic 74;		// javacard/framework/ISOException.throwIt(S)V
					goto_w L58;
				L39:	aload 7;
					invokevirtual 110;		// getReason()S
					sconst_2;
					if_scmpne_w L58;
				L40:	bspush 105;
					sconst_5;
					invokestatic 92;		// javacard/framework/Util.makeShort(BB)S
					invokestatic 74;		// javacard/framework/ISOException.throwIt(S)V
				L41:	goto_w L58;
				L42:	getfield_a_this 2;		// reference jcostest/JCOSTestApplet.cipher
					aload_2;
					aload_1;
					invokevirtual 97;		// getOffsetCdata()S
					sload_3;
					getfield_a_this 19;		// reference jcostest/JCOSTestApplet.b0
					sconst_0;
					invokevirtual 111;		// doFinal([BSS[BS)S
					sstore 7;
				L43:	aload_1;
					invokevirtual 107;		// setOutgoing()S
					pop;
					aload_1;
					sload 7;
					invokevirtual 108;		// setOutgoingLength(S)V
					aload_1;
					getfield_a_this 19;		// reference jcostest/JCOSTestApplet.b0
					sconst_0;
					sload 7;
					invokevirtual 109;		// sendBytesLong([BSS)V
				L44:	goto L58;
				L45:	astore 7;
				L46:	aload 7;
					invokevirtual 110;		// getReason()S
					sconst_5;
					if_scmpne L48;
				L47:	bspush 105;
					sconst_1;
					invokestatic 92;		// javacard/framework/Util.makeShort(BB)S
					invokestatic 74;		// javacard/framework/ISOException.throwIt(S)V
					goto L58;
				L48:	aload 7;
					invokevirtual 110;		// getReason()S
					sconst_1;
					if_scmpne L50;
				L49:	bspush 105;
					sconst_2;
					invokestatic 92;		// javacard/framework/Util.makeShort(BB)S
					invokestatic 74;		// javacard/framework/ISOException.throwIt(S)V
					goto L58;
				L50:	aload 7;
					invokevirtual 110;		// getReason()S
					sconst_4;
					if_scmpne L52;
				L51:	bspush 105;
					sconst_3;
					invokestatic 92;		// javacard/framework/Util.makeShort(BB)S
					invokestatic 74;		// javacard/framework/ISOException.throwIt(S)V
					goto L58;
				L52:	aload 7;
					invokevirtual 110;		// getReason()S
					sconst_3;
					if_scmpne L54;
				L53:	bspush 105;
					sconst_4;
					invokestatic 92;		// javacard/framework/Util.makeShort(BB)S
					invokestatic 74;		// javacard/framework/ISOException.throwIt(S)V
					goto L58;
				L54:	aload 7;
					invokevirtual 110;		// getReason()S
					sconst_2;
					if_scmpne L58;
				L55:	bspush 105;
					sconst_5;
					invokestatic 92;		// javacard/framework/Util.makeShort(BB)S
					invokestatic 74;		// javacard/framework/ISOException.throwIt(S)V
				L56:	goto L58;
				L57:	sspush 27270;
					invokestatic 74;		// javacard/framework/ISOException.throwIt(S)V
				L58:	return;
			.exceptionTable {
				// start_block end_block handler_block catch_type_index
				L4 L5 L6 102;
				L27 L29 L30 102;
				L42 L44 L45 102;
			}
		}

		.method public decrypt(Ljavacard/framework/APDU;[B)V 18 {
			.stack 6;
			.locals 5;

			.descriptor	Ljavacard/framework/APDU;	2.10;

				L0:	aload_1;
					invokevirtual 96;		// setIncomingAndReceive()S
					sstore_3;
				L1:	aload_2;
					sconst_2;
					baload;
					sstore 4;
				L2:	aload_2;
					sconst_3;
					baload;
					sstore 5;
				L3:	sload 4;
					stableswitch L39 1 6 L4 L39 L9 L12 L27 L33;
				L4:	aload_0;
					sload 5;
					sconst_0;
					invokestatic 103;		// javacardx/crypto/Cipher.getInstance(BZ)Ljavacardx/crypto/Cipher;
					putfield_a 2;		// reference jcostest/JCOSTestApplet.cipher
				L5:	goto_w L40;
				L6:	astore 6;
				L7:	sspush 27265;
					invokestatic 74;		// javacard/framework/ISOException.throwIt(S)V
				L8:	goto_w L40;
				L9:	getfield_a_this 2;		// reference jcostest/JCOSTestApplet.cipher
					ifnull L11;
				L10:	aload_2;
					sconst_0;
					getfield_a_this 2;		// reference jcostest/JCOSTestApplet.cipher
					invokevirtual 93;		// getAlgorithm()B
					bastore;
					aload_1;
					sconst_0;
					sconst_1;
					invokevirtual 75;		// setOutgoingAndSend(SS)V
					goto_w L40;
				L11:	sspush 25088;
					invokestatic 74;		// javacard/framework/ISOException.throwIt(S)V
					goto_w L40;
				L12:	aconst_null;
					astore 6;
				L13:	sload 5;
					sconst_1;
					if_scmpne L15;
				L14:	getfield_a_this 4;		// reference jcostest/JCOSTestApplet.testKey1
					astore 6;
					goto L22;
				L15:	sload 5;
					sconst_2;
					if_scmpne L17;
				L16:	getfield_a_this 5;		// reference jcostest/JCOSTestApplet.testKey2
					astore 6;
					goto L22;
				L17:	sload 5;
					sconst_3;
					if_scmpne L19;
				L18:	getfield_a_this 6;		// reference jcostest/JCOSTestApplet.testKey3
					astore 6;
					goto L22;
				L19:	sload 5;
					sconst_4;
					if_scmpne L21;
				L20:	getfield_a_this 7;		// reference jcostest/JCOSTestApplet.testKey4
					astore 6;
					goto L22;
				L21:	sspush 27267;
					invokestatic 74;		// javacard/framework/ISOException.throwIt(S)V
				L22:	aload 6;
					invokeinterface 1 88 3;		// javacard/security/Key
					ifeq L26;
				L23:	sload_3;
					ifgt L25;
				L24:	getfield_a_this 2;		// reference jcostest/JCOSTestApplet.cipher
					aload 6;
					sconst_1;
					invokevirtual 104;		// init(Ljavacard/security/Key;B)V
					goto_w L40;
				L25:	getfield_a_this 2;		// reference jcostest/JCOSTestApplet.cipher
					aload 6;
					sconst_1;
					aload_2;
					aload_1;
					invokevirtual 97;		// getOffsetCdata()S
					sload_3;
					invokevirtual 105;		// init(Ljavacard/security/Key;B[BSS)V
					goto L40;
				L26:	sspush 28609;
					invokestatic 74;		// javacard/framework/ISOException.throwIt(S)V
					goto L40;
				L27:	getfield_a_this 2;		// reference jcostest/JCOSTestApplet.cipher
					aload_2;
					aload_1;
					invokevirtual 97;		// getOffsetCdata()S
					sload_3;
					getfield_a_this 19;		// reference jcostest/JCOSTestApplet.b0
					sconst_0;
					invokevirtual 106;		// update([BSS[BS)S
					sstore 7;
				L28:	aload_1;
					invokevirtual 107;		// setOutgoing()S
					pop;
					aload_1;
					sload 7;
					invokevirtual 108;		// setOutgoingLength(S)V
					aload_1;
					getfield_a_this 19;		// reference jcostest/JCOSTestApplet.b0
					sconst_0;
					sload 7;
					invokevirtual 109;		// sendBytesLong([BSS)V
				L29:	goto L40;
				L30:	astore 7;
				L31:	sspush 27013;
					invokestatic 74;		// javacard/framework/ISOException.throwIt(S)V
				L32:	goto L40;
				L33:	getfield_a_this 2;		// reference jcostest/JCOSTestApplet.cipher
					aload_2;
					aload_1;
					invokevirtual 97;		// getOffsetCdata()S
					sload_3;
					getfield_a_this 19;		// reference jcostest/JCOSTestApplet.b0
					sconst_0;
					invokevirtual 111;		// doFinal([BSS[BS)S
					sstore 7;
				L34:	aload_1;
					invokevirtual 107;		// setOutgoing()S
					pop;
					aload_1;
					sload 7;
					invokevirtual 108;		// setOutgoingLength(S)V
					aload_1;
					getfield_a_this 19;		// reference jcostest/JCOSTestApplet.b0
					sconst_0;
					sload 7;
					invokevirtual 109;		// sendBytesLong([BSS)V
				L35:	goto L40;
				L36:	astore 7;
				L37:	sspush 27013;
					invokestatic 74;		// javacard/framework/ISOException.throwIt(S)V
				L38:	goto L40;
				L39:	sspush 27270;
					invokestatic 74;		// javacard/framework/ISOException.throwIt(S)V
				L40:	return;
			.exceptionTable {
				// start_block end_block handler_block catch_type_index
				L4 L5 L6 102;
				L27 L29 L30 102;
				L33 L35 L36 102;
			}
		}

		.method public derive(Ljavacard/framework/APDU;[B)V 19 {
			.stack 6;
			.locals 5;

			.descriptor	Ljavacard/framework/APDU;	2.10;

				L0:	aload_1;
					invokevirtual 96;		// setIncomingAndReceive()S
					sstore_3;
				L1:	aload_2;
					sconst_2;
					baload;
					sstore 4;
				L2:	aload_2;
					sconst_3;
					baload;
					sstore 5;
				L3:	sload 4;
					stableswitch L31 1 6 L4 L31 L9 L12 L31 L25;
				L4:	aload_0;
					sload 5;
					sconst_0;
					invokestatic 112;		// javacard/security/KeyAgreement.getInstance(BZ)Ljavacard/security/KeyAgreement;
					putfield_a 3;		// reference jcostest/JCOSTestApplet.ka
				L5:	goto_w L32;
				L6:	astore 6;
				L7:	sspush 27265;
					invokestatic 74;		// javacard/framework/ISOException.throwIt(S)V
				L8:	goto_w L32;
				L9:	getfield_a_this 3;		// reference jcostest/JCOSTestApplet.ka
					ifnull L11;
				L10:	aload_2;
					sconst_0;
					getfield_a_this 3;		// reference jcostest/JCOSTestApplet.ka
					invokevirtual 95;		// getAlgorithm()B
					bastore;
					aload_1;
					sconst_0;
					sconst_1;
					invokevirtual 75;		// setOutgoingAndSend(SS)V
					goto_w L32;
				L11:	sspush 25088;
					invokestatic 74;		// javacard/framework/ISOException.throwIt(S)V
					goto_w L32;
				L12:	aconst_null;
					astore 6;
				L13:	sload 5;
					sconst_1;
					if_scmpne L15;
				L14:	getfield_a_this 4;		// reference jcostest/JCOSTestApplet.testKey1
					astore 6;
					goto L22;
				L15:	sload 5;
					sconst_2;
					if_scmpne L17;
				L16:	getfield_a_this 5;		// reference jcostest/JCOSTestApplet.testKey2
					astore 6;
					goto L22;
				L17:	sload 5;
					sconst_3;
					if_scmpne L19;
				L18:	getfield_a_this 6;		// reference jcostest/JCOSTestApplet.testKey3
					astore 6;
					goto L22;
				L19:	sload 5;
					sconst_4;
					if_scmpne L21;
				L20:	getfield_a_this 7;		// reference jcostest/JCOSTestApplet.testKey4
					astore 6;
					goto L22;
				L21:	sspush 27267;
					invokestatic 74;		// javacard/framework/ISOException.throwIt(S)V
				L22:	aload 6;
					invokeinterface 1 88 3;		// javacard/security/Key
					ifeq L24;
				L23:	getfield_a_this 3;		// reference jcostest/JCOSTestApplet.ka
					aload 6;
					checkcast 0 113;		// T_CLASSORINTERFACE javacard/security/PrivateKey
					invokevirtual 114;		// init(Ljavacard/security/PrivateKey;)V
					goto L32;
				L24:	sspush 28609;
					invokestatic 74;		// javacard/framework/ISOException.throwIt(S)V
					goto L32;
				L25:	getfield_a_this 3;		// reference jcostest/JCOSTestApplet.ka
					aload_2;
					aload_1;
					invokevirtual 97;		// getOffsetCdata()S
					sload_3;
					getfield_a_this 19;		// reference jcostest/JCOSTestApplet.b0
					sconst_0;
					invokevirtual 115;		// generateSecret([BSS[BS)S
					sstore 7;
				L26:	aload_1;
					invokevirtual 107;		// setOutgoing()S
					pop;
					aload_1;
					sload 7;
					invokevirtual 108;		// setOutgoingLength(S)V
					aload_1;
					getfield_a_this 19;		// reference jcostest/JCOSTestApplet.b0
					sconst_0;
					sload 7;
					invokevirtual 109;		// sendBytesLong([BSS)V
				L27:	goto L32;
				L28:	astore 7;
				L29:	sspush 27013;
					invokestatic 74;		// javacard/framework/ISOException.throwIt(S)V
				L30:	goto L32;
				L31:	sspush 27270;
					invokestatic 74;		// javacard/framework/ISOException.throwIt(S)V
				L32:	return;
			.exceptionTable {
				// start_block end_block handler_block catch_type_index
				L4 L5 L6 102;
				L25 L27 L28 102;
			}
		}

		.method public sign(Ljavacard/framework/APDU;[B)V 20 {
			.stack 6;
			.locals 5;

			.descriptor	Ljavacard/framework/APDU;	2.10;

				L0:	aload_1;
					invokevirtual 96;		// setIncomingAndReceive()S
					sstore_3;
				L1:	aload_2;
					sconst_2;
					baload;
					sstore 4;
				L2:	aload_2;
					sconst_3;
					baload;
					sstore 5;
				L3:	sload 4;
					stableswitch L38 1 6 L4 L38 L9 L12 L27 L32;
				L4:	aload_0;
					sload 5;
					sconst_0;
					invokestatic 116;		// javacard/security/Signature.getInstance(BZ)Ljavacard/security/Signature;
					putfield_a 1;		// reference jcostest/JCOSTestApplet.signer
				L5:	goto_w L39;
				L6:	astore 6;
				L7:	sspush 27265;
					invokestatic 74;		// javacard/framework/ISOException.throwIt(S)V
				L8:	goto_w L39;
				L9:	getfield_a_this 2;		// reference jcostest/JCOSTestApplet.cipher
					ifnull L11;
				L10:	aload_2;
					sconst_0;
					getfield_a_this 2;		// reference jcostest/JCOSTestApplet.cipher
					invokevirtual 93;		// getAlgorithm()B
					bastore;
					aload_1;
					sconst_0;
					sconst_1;
					invokevirtual 75;		// setOutgoingAndSend(SS)V
					goto_w L39;
				L11:	sspush 25088;
					invokestatic 74;		// javacard/framework/ISOException.throwIt(S)V
					goto_w L39;
				L12:	aconst_null;
					astore 6;
				L13:	sload 5;
					sconst_1;
					if_scmpne L15;
				L14:	getfield_a_this 4;		// reference jcostest/JCOSTestApplet.testKey1
					astore 6;
					goto L22;
				L15:	sload 5;
					sconst_2;
					if_scmpne L17;
				L16:	getfield_a_this 5;		// reference jcostest/JCOSTestApplet.testKey2
					astore 6;
					goto L22;
				L17:	sload 5;
					sconst_3;
					if_scmpne L19;
				L18:	getfield_a_this 6;		// reference jcostest/JCOSTestApplet.testKey3
					astore 6;
					goto L22;
				L19:	sload 5;
					sconst_4;
					if_scmpne L21;
				L20:	getfield_a_this 7;		// reference jcostest/JCOSTestApplet.testKey4
					astore 6;
					goto L22;
				L21:	sspush 27267;
					invokestatic 74;		// javacard/framework/ISOException.throwIt(S)V
				L22:	aload 6;
					invokeinterface 1 88 3;		// javacard/security/Key
					ifeq L26;
				L23:	sload_3;
					ifne L25;
				L24:	getfield_a_this 1;		// reference jcostest/JCOSTestApplet.signer
					aload 6;
					sconst_1;
					invokevirtual 117;		// init(Ljavacard/security/Key;B)V
					goto L39;
				L25:	getfield_a_this 1;		// reference jcostest/JCOSTestApplet.signer
					aload 6;
					sconst_1;
					aload_2;
					aload_1;
					invokevirtual 97;		// getOffsetCdata()S
					sload_3;
					invokevirtual 118;		// init(Ljavacard/security/Key;B[BSS)V
					goto L39;
				L26:	sspush 28609;
					invokestatic 74;		// javacard/framework/ISOException.throwIt(S)V
					goto L39;
				L27:	getfield_a_this 1;		// reference jcostest/JCOSTestApplet.signer
					aload_2;
					aload_1;
					invokevirtual 97;		// getOffsetCdata()S
					sload_3;
					invokevirtual 119;		// update([BSS)V
				L28:	goto L39;
				L29:	astore 7;
				L30:	sspush 27013;
					invokestatic 74;		// javacard/framework/ISOException.throwIt(S)V
				L31:	goto L39;
				L32:	getfield_a_this 1;		// reference jcostest/JCOSTestApplet.signer
					aload_2;
					aload_1;
					invokevirtual 97;		// getOffsetCdata()S
					sload_3;
					getfield_a_this 19;		// reference jcostest/JCOSTestApplet.b0
					sconst_0;
					invokevirtual 120;		// sign([BSS[BS)S
					sstore 7;
				L33:	aload_1;
					invokevirtual 107;		// setOutgoing()S
					pop;
					aload_1;
					sload 7;
					invokevirtual 108;		// setOutgoingLength(S)V
					aload_1;
					getfield_a_this 19;		// reference jcostest/JCOSTestApplet.b0
					sconst_0;
					sload 7;
					invokevirtual 109;		// sendBytesLong([BSS)V
				L34:	goto L39;
				L35:	astore 7;
				L36:	sspush 27013;
					invokestatic 74;		// javacard/framework/ISOException.throwIt(S)V
				L37:	goto L39;
				L38:	sspush 27270;
					invokestatic 74;		// javacard/framework/ISOException.throwIt(S)V
				L39:	return;
			.exceptionTable {
				// start_block end_block handler_block catch_type_index
				L4 L5 L6 102;
				L27 L28 L29 102;
				L32 L34 L35 102;
			}
		}

		.method public verify(Ljavacard/framework/APDU;[B)V 21 {
			.stack 7;
			.locals 5;

			.descriptor	Ljavacard/framework/APDU;	2.10;

				L0:	aload_1;
					invokevirtual 96;		// setIncomingAndReceive()S
					sstore_3;
				L1:	aload_2;
					sconst_2;
					baload;
					sstore 4;
				L2:	aload_2;
					sconst_3;
					baload;
					sstore 5;
				L3:	sload 4;
					stableswitch L42 1 6 L4 L42 L9 L12 L27 L32;
				L4:	aload_0;
					sload 5;
					sconst_0;
					invokestatic 116;		// javacard/security/Signature.getInstance(BZ)Ljavacard/security/Signature;
					putfield_a 1;		// reference jcostest/JCOSTestApplet.signer
				L5:	goto_w L43;
				L6:	astore 6;
				L7:	sspush 27265;
					invokestatic 74;		// javacard/framework/ISOException.throwIt(S)V
				L8:	goto_w L43;
				L9:	getfield_a_this 2;		// reference jcostest/JCOSTestApplet.cipher
					ifnull L11;
				L10:	aload_2;
					sconst_0;
					getfield_a_this 1;		// reference jcostest/JCOSTestApplet.signer
					invokevirtual 94;		// getAlgorithm()B
					bastore;
					aload_1;
					sconst_0;
					sconst_1;
					invokevirtual 75;		// setOutgoingAndSend(SS)V
					goto_w L43;
				L11:	sspush 25088;
					invokestatic 74;		// javacard/framework/ISOException.throwIt(S)V
					goto_w L43;
				L12:	aconst_null;
					astore 6;
				L13:	sload 5;
					sconst_1;
					if_scmpne L15;
				L14:	getfield_a_this 4;		// reference jcostest/JCOSTestApplet.testKey1
					astore 6;
					goto L22;
				L15:	sload 5;
					sconst_2;
					if_scmpne L17;
				L16:	getfield_a_this 5;		// reference jcostest/JCOSTestApplet.testKey2
					astore 6;
					goto L22;
				L17:	sload 5;
					sconst_3;
					if_scmpne L19;
				L18:	getfield_a_this 6;		// reference jcostest/JCOSTestApplet.testKey3
					astore 6;
					goto L22;
				L19:	sload 5;
					sconst_4;
					if_scmpne L21;
				L20:	getfield_a_this 7;		// reference jcostest/JCOSTestApplet.testKey4
					astore 6;
					goto L22;
				L21:	sspush 27267;
					invokestatic 74;		// javacard/framework/ISOException.throwIt(S)V
				L22:	aload 6;
					invokeinterface 1 88 3;		// javacard/security/Key
					ifeq L26;
				L23:	sload_3;
					ifne L25;
				L24:	getfield_a_this 1;		// reference jcostest/JCOSTestApplet.signer
					aload 6;
					sconst_2;
					invokevirtual 117;		// init(Ljavacard/security/Key;B)V
					goto L43;
				L25:	getfield_a_this 1;		// reference jcostest/JCOSTestApplet.signer
					aload 6;
					sconst_2;
					aload_2;
					aload_1;
					invokevirtual 97;		// getOffsetCdata()S
					sload_3;
					invokevirtual 118;		// init(Ljavacard/security/Key;B[BSS)V
					goto L43;
				L26:	sspush 28609;
					invokestatic 74;		// javacard/framework/ISOException.throwIt(S)V
					goto L43;
				L27:	getfield_a_this 1;		// reference jcostest/JCOSTestApplet.signer
					aload_2;
					aload_1;
					invokevirtual 97;		// getOffsetCdata()S
					sload_3;
					invokevirtual 119;		// update([BSS)V
				L28:	goto L43;
				L29:	astore 7;
				L30:	sspush 27013;
					invokestatic 74;		// javacard/framework/ISOException.throwIt(S)V
				L31:	goto L43;
				L32:	getfield_a_this 18;		// reference jcostest/JCOSTestApplet.arbitraryData
					ifnonnull L34;
				L33:	sspush 27012;
					invokestatic 74;		// javacard/framework/ISOException.throwIt(S)V
				L34:	getfield_a_this 1;		// reference jcostest/JCOSTestApplet.signer
					getfield_a_this 18;		// reference jcostest/JCOSTestApplet.arbitraryData
					sconst_0;
					getfield_a_this 18;		// reference jcostest/JCOSTestApplet.arbitraryData
					arraylength;
					aload_2;
					aload_1;
					invokevirtual 97;		// getOffsetCdata()S
					sload_3;
					invokevirtual 121;		// verify([BSS[BSS)Z
					ifeq L36;
				L35:	aload_2;
					sconst_0;
					sconst_1;
					bastore;
					goto L37;
				L36:	aload_2;
					sconst_0;
					sconst_0;
					bastore;
				L37:	aload_1;
					sconst_0;
					sconst_1;
					invokevirtual 75;		// setOutgoingAndSend(SS)V
				L38:	goto L43;
				L39:	astore 7;
				L40:	sspush 27013;
					invokestatic 74;		// javacard/framework/ISOException.throwIt(S)V
				L41:	goto L43;
				L42:	sspush 27270;
					invokestatic 74;		// javacard/framework/ISOException.throwIt(S)V
				L43:	return;
			.exceptionTable {
				// start_block end_block handler_block catch_type_index
				L4 L5 L6 102;
				L27 L28 L29 102;
				L32 L38 L39 102;
			}
		}

		.method public setData(Ljavacard/framework/APDU;[B)V 22 {
			.stack 5;
			.locals 3;

			.descriptor	Ljavacard/framework/APDU;	2.10;

				L0:	sconst_0;
					sstore_3;
				L1:	aload_2;
					sconst_2;
					baload;
					sstore 4;
				L2:	aload_2;
					sconst_3;
					baload;
					sstore 5;
				L3:	sload 4;
					stableswitch L14 2 8 L10 L11 L14 L14 L14 L4 L7;
				L4:	aload_1;
					invokevirtual 96;		// setIncomingAndReceive()S
					sstore_3;
					sload_3;
					ifgt L6;
				L5:	sspush 26368;
					invokestatic 74;		// javacard/framework/ISOException.throwIt(S)V
				L6:	aload_2;
					aload_1;
					invokevirtual 97;		// getOffsetCdata()S
					getfield_a_this 20;		// reference jcostest/JCOSTestApplet.b1
					sconst_0;
					sload_3;
					invokestatic 122;		// javacard/framework/Util.arrayCopyNonAtomic([BS[BSS)S
					pop;
					goto L15;
				L7:	aload_1;
					invokevirtual 96;		// setIncomingAndReceive()S
					sstore_3;
					sload_3;
					ifgt L9;
				L8:	sspush 26368;
					invokestatic 74;		// javacard/framework/ISOException.throwIt(S)V
				L9:	aload_0;
					aconst_null;
					putfield_a 18;		// reference jcostest/JCOSTestApplet.arbitraryData
					aload_0;
					sload_3;
					newarray 11;
					putfield_a 18;		// reference jcostest/JCOSTestApplet.arbitraryData
					aload_2;
					aload_1;
					invokevirtual 97;		// getOffsetCdata()S
					getfield_a_this 18;		// reference jcostest/JCOSTestApplet.arbitraryData
					sconst_0;
					sload_3;
					invokestatic 123;		// jcostest/AlternateKM.setData([BS[BSS)V
					goto L15;
				L10:	aload_1;
					invokevirtual 107;		// setOutgoing()S
					pop;
					aload_1;
					getfield_a_this 20;		// reference jcostest/JCOSTestApplet.b1
					arraylength;
					invokevirtual 108;		// setOutgoingLength(S)V
					aload_1;
					getfield_a_this 20;		// reference jcostest/JCOSTestApplet.b1
					sconst_0;
					getfield_a_this 20;		// reference jcostest/JCOSTestApplet.b1
					arraylength;
					invokevirtual 109;		// sendBytesLong([BSS)V
					goto L15;
				L11:	getfield_a_this 18;		// reference jcostest/JCOSTestApplet.arbitraryData
					ifnonnull L13;
				L12:	sspush 27267;
					invokestatic 74;		// javacard/framework/ISOException.throwIt(S)V
					goto L15;
				L13:	aload_2;
					sconst_0;
					getfield_a_this 18;		// reference jcostest/JCOSTestApplet.arbitraryData
					arraylength;
					invokestatic 124;		// javacard/framework/Util.setShort([BSS)S
					pop;
					aload_1;
					sconst_0;
					sconst_2;
					invokevirtual 75;		// setOutgoingAndSend(SS)V
					goto L15;
				L14:	sspush 27270;
					invokestatic 74;		// javacard/framework/ISOException.throwIt(S)V
				L15:	return;
		}

		.method public doHash(Ljavacard/framework/APDU;[B)V 23 {
			.stack 6;
			.locals 4;

			.descriptor	Ljavacard/framework/APDU;	2.10;

				L0:	aload_1;
					invokevirtual 96;		// setIncomingAndReceive()S
					sstore_3;
				L1:	aload_2;
					sconst_2;
					baload;
					sstore 4;
				L2:	aload_2;
					sconst_3;
					baload;
					sstore 5;
				L3:	sload 4;
					stableswitch L24 1 6 L4 L24 L9 L12 L13 L18;
				L4:	aload_0;
					sload 5;
					sconst_0;
					invokestatic 125;		// javacard/security/MessageDigest.getInstance(BZ)Ljavacard/security/MessageDigest;
					putfield_a 0;		// reference jcostest/JCOSTestApplet.md
				L5:	goto_w L25;
				L6:	astore 6;
				L7:	sspush 27265;
					invokestatic 74;		// javacard/framework/ISOException.throwIt(S)V
				L8:	goto L25;
				L9:	getfield_a_this 0;		// reference jcostest/JCOSTestApplet.md
					ifnull L11;
				L10:	aload_2;
					sconst_0;
					getfield_a_this 0;		// reference jcostest/JCOSTestApplet.md
					invokevirtual 126;		// getAlgorithm()B
					bastore;
					aload_1;
					sconst_0;
					sconst_1;
					invokevirtual 75;		// setOutgoingAndSend(SS)V
					goto L25;
				L11:	sspush 25088;
					invokestatic 74;		// javacard/framework/ISOException.throwIt(S)V
					goto L25;
				L12:	getfield_a_this 0;		// reference jcostest/JCOSTestApplet.md
					invokevirtual 127;		// reset()V
					goto L25;
				L13:	getfield_a_this 0;		// reference jcostest/JCOSTestApplet.md
					aload_2;
					aload_1;
					invokevirtual 97;		// getOffsetCdata()S
					sload_3;
					invokevirtual 128;		// update([BSS)V
				L14:	goto L25;
				L15:	astore 6;
				L16:	sspush 27013;
					invokestatic 74;		// javacard/framework/ISOException.throwIt(S)V
				L17:	goto L25;
				L18:	getfield_a_this 0;		// reference jcostest/JCOSTestApplet.md
					aload_2;
					aload_1;
					invokevirtual 97;		// getOffsetCdata()S
					sload_3;
					getfield_a_this 19;		// reference jcostest/JCOSTestApplet.b0
					sconst_0;
					invokevirtual 129;		// doFinal([BSS[BS)S
					sstore 6;
				L19:	aload_1;
					invokevirtual 107;		// setOutgoing()S
					pop;
					aload_1;
					sload 6;
					invokevirtual 108;		// setOutgoingLength(S)V
					aload_1;
					getfield_a_this 19;		// reference jcostest/JCOSTestApplet.b0
					sconst_0;
					sload 6;
					invokevirtual 109;		// sendBytesLong([BSS)V
				L20:	goto L25;
				L21:	astore 6;
				L22:	sspush 27013;
					invokestatic 74;		// javacard/framework/ISOException.throwIt(S)V
				L23:	goto L25;
				L24:	sspush 27270;
					invokestatic 74;		// javacard/framework/ISOException.throwIt(S)V
				L25:	return;
			.exceptionTable {
				// start_block end_block handler_block catch_type_index
				L4 L5 L6 102;
				L13 L14 L15 102;
				L18 L20 L21 102;
			}
		}

		.method public setKey(Ljavacard/security/Key;BB[BSS)Z 24 {
			.stack 4;
			.locals 0;

			.descriptor	Ljavacard/security/Key;	1.0;

				L0:	sload_3;
					slookupswitch L15 10 1 L6 2 L5 3 L4 11 L13 12 L7 13 L3 14 L2 15 L1 30 L11 31 L9;
				L1:	aload_1;
					checkcast 0 47;		// T_CLASSORINTERFACE javacard/security/AESKey
					aload 4;
					sload 5;
					invokeinterface 3 47 4;		// javacard/security/AESKey
					sconst_1;
					sreturn;
				L2:	aload_1;
					checkcast 0 47;		// T_CLASSORINTERFACE javacard/security/AESKey
					aload 4;
					sload 5;
					invokeinterface 3 47 4;		// javacard/security/AESKey
					sconst_1;
					sreturn;
				L3:	aload_1;
					checkcast 0 47;		// T_CLASSORINTERFACE javacard/security/AESKey
					aload 4;
					sload 5;
					invokeinterface 3 47 4;		// javacard/security/AESKey
					sconst_1;
					sreturn;
				L4:	aload_1;
					checkcast 0 48;		// T_CLASSORINTERFACE javacard/security/DESKey
					aload 4;
					sload 5;
					invokeinterface 3 48 5;		// javacard/security/DESKey
					sconst_1;
					sreturn;
				L5:	aload_1;
					checkcast 0 48;		// T_CLASSORINTERFACE javacard/security/DESKey
					aload 4;
					sload 5;
					invokeinterface 3 48 5;		// javacard/security/DESKey
					sconst_1;
					sreturn;
				L6:	aload_1;
					checkcast 0 48;		// T_CLASSORINTERFACE javacard/security/DESKey
					aload 4;
					sload 5;
					invokeinterface 3 48 5;		// javacard/security/DESKey
					sconst_1;
					sreturn;
				L7:	aload_0;
					aload_1;
					checkcast 0 52;		// T_CLASSORINTERFACE javacard/security/ECKey
					sload_2;
					invokevirtual 130;		// initECCurveParameters(Ljavacard/security/ECKey;B)Z
					ifeq L15;
				L8:	aload_1;
					checkcast 0 51;		// T_CLASSORINTERFACE javacard/security/ECPrivateKey
					aload 4;
					sload 5;
					sload 6;
					invokeinterface 4 51 18;		// javacard/security/ECPrivateKey
					sconst_1;
					sreturn;
				L9:	aload_0;
					aload_1;
					checkcast 0 52;		// T_CLASSORINTERFACE javacard/security/ECKey
					sload_2;
					invokevirtual 130;		// initECCurveParameters(Ljavacard/security/ECKey;B)Z
					ifeq L15;
				L10:	aload_1;
					checkcast 0 51;		// T_CLASSORINTERFACE javacard/security/ECPrivateKey
					aload 4;
					sload 5;
					sload 6;
					invokeinterface 4 51 18;		// javacard/security/ECPrivateKey
					sconst_1;
					sreturn;
				L11:	aload_0;
					aload_1;
					checkcast 0 52;		// T_CLASSORINTERFACE javacard/security/ECKey
					sload_2;
					invokevirtual 130;		// initECCurveParameters(Ljavacard/security/ECKey;B)Z
					ifeq L15;
				L12:	aload_1;
					checkcast 0 51;		// T_CLASSORINTERFACE javacard/security/ECPrivateKey
					aload 4;
					sload 5;
					sload 6;
					invokeinterface 4 51 18;		// javacard/security/ECPrivateKey
					sconst_1;
					sreturn;
				L13:	aload_0;
					aload_1;
					checkcast 0 52;		// T_CLASSORINTERFACE javacard/security/ECKey
					sload_2;
					invokevirtual 130;		// initECCurveParameters(Ljavacard/security/ECKey;B)Z
					ifeq L15;
				L14:	aload_1;
					checkcast 0 49;		// T_CLASSORINTERFACE javacard/security/ECPublicKey
					aload 4;
					sload 5;
					sload 6;
					invokeinterface 4 49 18;		// javacard/security/ECPublicKey
					sconst_1;
					sreturn;
				L15:	sconst_0;
					sreturn;
		}

		.method public initECCurveParameters(Ljavacard/security/ECKey;B)Z 25 {
			.stack 4;
			.locals 1;

			.descriptor	Ljavacard/security/ECKey;	1.17;

				L0:	sload_2;
					sconst_1;
					if_scmpne L2;
				L1:	aload_1;
					getstatic_a 53;		// reference jcostest/Constants.ansix9p256r1_a
					sconst_0;
					getstatic_a 53;		// reference jcostest/Constants.ansix9p256r1_a
					arraylength;
					invokeinterface 4 52 3;		// javacard/security/ECKey
					aload_1;
					getstatic_a 54;		// reference jcostest/Constants.ansix9p256r1_b
					sconst_0;
					getstatic_a 54;		// reference jcostest/Constants.ansix9p256r1_b
					arraylength;
					invokeinterface 4 52 4;		// javacard/security/ECKey
					aload_1;
					getstatic_a 56;		// reference jcostest/Constants.ansix9p256r1_g
					sconst_0;
					getstatic_a 56;		// reference jcostest/Constants.ansix9p256r1_g
					arraylength;
					invokeinterface 4 52 5;		// javacard/security/ECKey
					aload_1;
					getstatic_a 57;		// reference jcostest/Constants.ansix9p256r1_r
					sconst_0;
					getstatic_a 57;		// reference jcostest/Constants.ansix9p256r1_r
					arraylength;
					invokeinterface 4 52 6;		// javacard/security/ECKey
					aload_1;
					getstatic_a 55;		// reference jcostest/Constants.ansix9p256r1_field
					sconst_0;
					getstatic_a 55;		// reference jcostest/Constants.ansix9p256r1_field
					arraylength;
					invokeinterface 4 52 0;		// javacard/security/ECKey
					aload_1;
					sconst_1;
					invokeinterface 2 52 7;		// javacard/security/ECKey
					sconst_1;
					sreturn;
				L2:	sload_2;
					sconst_2;
					if_scmpne L4;
				L3:	aload_1;
					getstatic_a 58;		// reference jcostest/Constants.ansix9p384r1_a
					sconst_0;
					getstatic_a 58;		// reference jcostest/Constants.ansix9p384r1_a
					arraylength;
					invokeinterface 4 52 3;		// javacard/security/ECKey
					aload_1;
					getstatic_a 59;		// reference jcostest/Constants.ansix9p384r1_b
					sconst_0;
					getstatic_a 59;		// reference jcostest/Constants.ansix9p384r1_b
					arraylength;
					invokeinterface 4 52 4;		// javacard/security/ECKey
					aload_1;
					getstatic_a 61;		// reference jcostest/Constants.ansix9p384r1_g
					sconst_0;
					getstatic_a 61;		// reference jcostest/Constants.ansix9p384r1_g
					arraylength;
					invokeinterface 4 52 5;		// javacard/security/ECKey
					aload_1;
					getstatic_a 62;		// reference jcostest/Constants.ansix9p384r1_r
					sconst_0;
					getstatic_a 62;		// reference jcostest/Constants.ansix9p384r1_r
					arraylength;
					invokeinterface 4 52 6;		// javacard/security/ECKey
					aload_1;
					getstatic_a 60;		// reference jcostest/Constants.ansix9p384r1_field
					sconst_0;
					getstatic_a 60;		// reference jcostest/Constants.ansix9p384r1_field
					arraylength;
					invokeinterface 4 52 0;		// javacard/security/ECKey
					aload_1;
					sconst_1;
					invokeinterface 2 52 7;		// javacard/security/ECKey
					sconst_1;
					sreturn;
				L4:	sload_2;
					sconst_3;
					if_scmpne L6;
				L5:	aload_1;
					getstatic_a 63;		// reference jcostest/Constants.ansix9p521r1_a
					sconst_0;
					getstatic_a 63;		// reference jcostest/Constants.ansix9p521r1_a
					arraylength;
					invokeinterface 4 52 3;		// javacard/security/ECKey
					aload_1;
					getstatic_a 64;		// reference jcostest/Constants.ansix9p521r1_b
					sconst_0;
					getstatic_a 64;		// reference jcostest/Constants.ansix9p521r1_b
					arraylength;
					invokeinterface 4 52 4;		// javacard/security/ECKey
					aload_1;
					getstatic_a 67;		// reference jcostest/Constants.ansix9p521r1_g
					sconst_0;
					getstatic_a 67;		// reference jcostest/Constants.ansix9p521r1_g
					arraylength;
					invokeinterface 4 52 5;		// javacard/security/ECKey
					aload_1;
					getstatic_a 21;		// reference jcostest/Constants.ansix9p521r1_r
					sconst_0;
					getstatic_a 21;		// reference jcostest/Constants.ansix9p521r1_r
					arraylength;
					invokeinterface 4 52 6;		// javacard/security/ECKey
					aload_1;
					getstatic_a 66;		// reference jcostest/Constants.ansix9p521r1_field
					sconst_0;
					getstatic_a 66;		// reference jcostest/Constants.ansix9p521r1_field
					arraylength;
					invokeinterface 4 52 0;		// javacard/security/ECKey
					aload_1;
					sconst_1;
					invokeinterface 2 52 7;		// javacard/security/ECKey
					sconst_1;
					sreturn;
				L6:	sload_2;
					sconst_4;
					if_scmpne L8;
				L7:	aload_1;
					getstatic_a 22;		// reference jcostest/Constants.SECP256K1_A
					sconst_0;
					getstatic_a 22;		// reference jcostest/Constants.SECP256K1_A
					arraylength;
					invokeinterface 4 52 3;		// javacard/security/ECKey
					aload_1;
					getstatic_a 23;		// reference jcostest/Constants.SECP256K1_B
					sconst_0;
					getstatic_a 23;		// reference jcostest/Constants.SECP256K1_B
					arraylength;
					invokeinterface 4 52 4;		// javacard/security/ECKey
					aload_1;
					getstatic_a 25;		// reference jcostest/Constants.SECP256K1_G
					sconst_0;
					getstatic_a 25;		// reference jcostest/Constants.SECP256K1_G
					arraylength;
					invokeinterface 4 52 5;		// javacard/security/ECKey
					aload_1;
					getstatic_a 26;		// reference jcostest/Constants.SECP256K1_R
					sconst_0;
					getstatic_a 26;		// reference jcostest/Constants.SECP256K1_R
					arraylength;
					invokeinterface 4 52 6;		// javacard/security/ECKey
					aload_1;
					getstatic_a 24;		// reference jcostest/Constants.SECP256K1_FIELD
					sconst_0;
					getstatic_a 24;		// reference jcostest/Constants.SECP256K1_FIELD
					arraylength;
					invokeinterface 4 52 0;		// javacard/security/ECKey
					aload_1;
					sconst_1;
					invokeinterface 2 52 7;		// javacard/security/ECKey
					sconst_1;
					sreturn;
				L8:	sload_2;
					sconst_5;
					if_scmpne L10;
				L9:	aload_1;
					getstatic_a 27;		// reference jcostest/Constants.brainpoolP256r1_a
					sconst_0;
					getstatic_a 27;		// reference jcostest/Constants.brainpoolP256r1_a
					arraylength;
					invokeinterface 4 52 3;		// javacard/security/ECKey
					aload_1;
					getstatic_a 28;		// reference jcostest/Constants.brainpoolP256r1_b
					sconst_0;
					getstatic_a 28;		// reference jcostest/Constants.brainpoolP256r1_b
					arraylength;
					invokeinterface 4 52 4;		// javacard/security/ECKey
					aload_1;
					getstatic_a 30;		// reference jcostest/Constants.brainpoolP256r1_g
					sconst_0;
					getstatic_a 30;		// reference jcostest/Constants.brainpoolP256r1_g
					arraylength;
					invokeinterface 4 52 5;		// javacard/security/ECKey
					aload_1;
					getstatic_a 31;		// reference jcostest/Constants.brainpoolP256r1_r
					sconst_0;
					getstatic_a 31;		// reference jcostest/Constants.brainpoolP256r1_r
					arraylength;
					invokeinterface 4 52 6;		// javacard/security/ECKey
					aload_1;
					getstatic_a 29;		// reference jcostest/Constants.brainpoolP256r1_field
					sconst_0;
					getstatic_a 29;		// reference jcostest/Constants.brainpoolP256r1_field
					arraylength;
					invokeinterface 4 52 0;		// javacard/security/ECKey
					aload_1;
					sconst_1;
					invokeinterface 2 52 7;		// javacard/security/ECKey
					sconst_1;
					sreturn;
				L10:	sload_2;
					bspush 6;
					if_scmpne L12;
				L11:	aload_1;
					getstatic_a 32;		// reference jcostest/Constants.brainpoolP384r1_a
					sconst_0;
					getstatic_a 32;		// reference jcostest/Constants.brainpoolP384r1_a
					arraylength;
					invokeinterface 4 52 3;		// javacard/security/ECKey
					aload_1;
					getstatic_a 33;		// reference jcostest/Constants.brainpoolP384r1_b
					sconst_0;
					getstatic_a 33;		// reference jcostest/Constants.brainpoolP384r1_b
					arraylength;
					invokeinterface 4 52 4;		// javacard/security/ECKey
					aload_1;
					getstatic_a 35;		// reference jcostest/Constants.brainpoolP384r1_g
					sconst_0;
					getstatic_a 35;		// reference jcostest/Constants.brainpoolP384r1_g
					arraylength;
					invokeinterface 4 52 5;		// javacard/security/ECKey
					aload_1;
					getstatic_a 36;		// reference jcostest/Constants.brainpoolP384r1_r
					sconst_0;
					getstatic_a 36;		// reference jcostest/Constants.brainpoolP384r1_r
					arraylength;
					invokeinterface 4 52 6;		// javacard/security/ECKey
					aload_1;
					getstatic_a 34;		// reference jcostest/Constants.brainpoolP384r1_field
					sconst_0;
					getstatic_a 34;		// reference jcostest/Constants.brainpoolP384r1_field
					arraylength;
					invokeinterface 4 52 0;		// javacard/security/ECKey
					aload_1;
					sconst_1;
					invokeinterface 2 52 7;		// javacard/security/ECKey
					sconst_1;
					sreturn;
				L12:	sload_2;
					bspush 7;
					if_scmpne_w L38;
				L13:	aload_1;
					getstatic_a 37;		// reference jcostest/Constants.brainpoolP512r1_a
					sconst_0;
					getstatic_a 37;		// reference jcostest/Constants.brainpoolP512r1_a
					arraylength;
					invokeinterface 4 52 3;		// javacard/security/ECKey
				L14:	goto L17;
				L15:	astore_3;
				L16:	bspush 111;
					bspush -79;
					invokestatic 92;		// javacard/framework/Util.makeShort(BB)S
					invokestatic 74;		// javacard/framework/ISOException.throwIt(S)V
				L17:	aload_1;
					getstatic_a 38;		// reference jcostest/Constants.brainpoolP512r1_b
					sconst_0;
					getstatic_a 38;		// reference jcostest/Constants.brainpoolP512r1_b
					arraylength;
					invokeinterface 4 52 4;		// javacard/security/ECKey
				L18:	goto L21;
				L19:	astore_3;
				L20:	bspush 111;
					bspush -78;
					invokestatic 92;		// javacard/framework/Util.makeShort(BB)S
					invokestatic 74;		// javacard/framework/ISOException.throwIt(S)V
				L21:	aload_1;
					getstatic_a 40;		// reference jcostest/Constants.brainpoolP512r1_g
					sconst_0;
					getstatic_a 40;		// reference jcostest/Constants.brainpoolP512r1_g
					arraylength;
					invokeinterface 4 52 5;		// javacard/security/ECKey
				L22:	goto L25;
				L23:	astore_3;
				L24:	bspush 111;
					bspush -77;
					invokestatic 92;		// javacard/framework/Util.makeShort(BB)S
					invokestatic 74;		// javacard/framework/ISOException.throwIt(S)V
				L25:	aload_1;
					getstatic_a 41;		// reference jcostest/Constants.brainpoolP512r1_r
					sconst_0;
					getstatic_a 41;		// reference jcostest/Constants.brainpoolP512r1_r
					arraylength;
					invokeinterface 4 52 6;		// javacard/security/ECKey
				L26:	goto L29;
				L27:	astore_3;
				L28:	bspush 111;
					bspush -76;
					invokestatic 92;		// javacard/framework/Util.makeShort(BB)S
					invokestatic 74;		// javacard/framework/ISOException.throwIt(S)V
				L29:	aload_1;
					getstatic_a 39;		// reference jcostest/Constants.brainpoolP512r1_field
					sconst_0;
					getstatic_a 39;		// reference jcostest/Constants.brainpoolP512r1_field
					arraylength;
					invokeinterface 4 52 0;		// javacard/security/ECKey
				L30:	goto L33;
				L31:	astore_3;
				L32:	bspush 111;
					bspush -75;
					invokestatic 92;		// javacard/framework/Util.makeShort(BB)S
					invokestatic 74;		// javacard/framework/ISOException.throwIt(S)V
				L33:	aload_1;
					sconst_1;
					invokeinterface 2 52 7;		// javacard/security/ECKey
				L34:	goto L37;
				L35:	astore_3;
				L36:	bspush 111;
					bspush -74;
					invokestatic 92;		// javacard/framework/Util.makeShort(BB)S
					invokestatic 74;		// javacard/framework/ISOException.throwIt(S)V
				L37:	sconst_1;
					sreturn;
				L38:	sconst_0;
					sreturn;
			.exceptionTable {
				// start_block end_block handler_block catch_type_index
				L13 L14 L15 131;
				L17 L18 L19 131;
				L21 L22 L23 131;
				L25 L26 L27 131;
				L29 L30 L31 131;
				L33 L34 L35 131;
			}
		}

	}

}
